{
    "game_id": "139131",
    "game_name": "Hoplomachus: Rise of Rome",
    "bgg_link": "https://boardgamegeek.com/boardgame/139131",
    "sgoyt_entries": [
        {
            "geeklist_id": "174241",
            "geeklist_item_id": "3260016",
            "year_month": "2014/06",
            "year": "2014",
            "month": "06",
            "geeklist_item_link": "https://boardgamegeek.com/geeklist/174241/item/3260016#item3260016",
            "geeklist_host": "ReggieMcFly",
            "contributor": "kerskine"
        },
        {
            "geeklist_id": "178257",
            "geeklist_item_id": "3450552",
            "year_month": "2014/09",
            "year": "2014",
            "month": "09",
            "geeklist_item_link": "https://boardgamegeek.com/geeklist/178257/item/3450552#item3450552",
            "geeklist_host": "Malaiser",
            "contributor": "permagoof"
        },
        {
            "geeklist_id": "179645",
            "geeklist_item_id": "3545951",
            "year_month": "2014/11",
            "year": "2014",
            "month": "11",
            "geeklist_item_link": "https://boardgamegeek.com/geeklist/179645/item/3545951#item3545951",
            "geeklist_host": "garyrbrooks",
            "contributor": "theritzes"
        },
        {
            "geeklist_id": "179645",
            "geeklist_item_id": "3547850",
            "year_month": "2014/11",
            "year": "2014",
            "month": "11",
            "geeklist_item_link": "https://boardgamegeek.com/geeklist/179645/item/3547850#item3547850",
            "geeklist_host": "garyrbrooks",
            "contributor": "eastwoodk"
        },
        {
            "geeklist_id": "182573",
            "geeklist_item_id": "3632429",
            "year_month": "2014/12",
            "year": "2014",
            "month": "12",
            "geeklist_item_link": "https://boardgamegeek.com/geeklist/182573/item/3632429#item3632429",
            "geeklist_host": "Ryanmobile",
            "contributor": "kerskine"
        },
        {
            "geeklist_id": "183994",
            "geeklist_item_id": "3643251",
            "year_month": "2015/01",
            "year": "2015",
            "month": "01",
            "geeklist_item_link": "https://boardgamegeek.com/geeklist/183994/item/3643251#item3643251",
            "geeklist_host": "bikefreak",
            "contributor": "eastwoodk"
        },
        {
            "geeklist_id": "183994",
            "geeklist_item_id": "3678167",
            "year_month": "2015/01",
            "year": "2015",
            "month": "01",
            "geeklist_item_link": "https://boardgamegeek.com/geeklist/183994/item/3678167#item3678167",
            "geeklist_host": "bikefreak",
            "contributor": "eastwoodk"
        },
        {
            "geeklist_id": "183994",
            "geeklist_item_id": "3679242",
            "year_month": "2015/01",
            "year": "2015",
            "month": "01",
            "geeklist_item_link": "https://boardgamegeek.com/geeklist/183994/item/3679242#item3679242",
            "geeklist_host": "bikefreak",
            "contributor": "permagoof"
        },
        {
            "geeklist_id": "186058",
            "geeklist_item_id": "3868592",
            "year_month": "2015/04",
            "year": "2015",
            "month": "04",
            "geeklist_item_link": "https://boardgamegeek.com/geeklist/186058/item/3868592#item3868592",
            "geeklist_host": "garyrbrooks",
            "contributor": "repairmanjack"
        },
        {
            "geeklist_id": "186058",
            "geeklist_item_id": "3870524",
            "year_month": "2015/04",
            "year": "2015",
            "month": "04",
            "geeklist_item_link": "https://boardgamegeek.com/geeklist/186058/item/3870524#item3870524",
            "geeklist_host": "garyrbrooks",
            "contributor": "repairmanjack"
        },
        {
            "geeklist_id": "186058",
            "geeklist_item_id": "3871838",
            "year_month": "2015/04",
            "year": "2015",
            "month": "04",
            "geeklist_item_link": "https://boardgamegeek.com/geeklist/186058/item/3871838#item3871838",
            "geeklist_host": "garyrbrooks",
            "contributor": "repairmanjack"
        },
        {
            "geeklist_id": "190679",
            "geeklist_item_id": "3880497",
            "year_month": "2015/05",
            "year": "2015",
            "month": "05",
            "geeklist_item_link": "https://boardgamegeek.com/geeklist/190679/item/3880497#item3880497",
            "geeklist_host": "reverendunclebastard",
            "contributor": "repairmanjack"
        },
        {
            "geeklist_id": "190679",
            "geeklist_item_id": "3894798",
            "year_month": "2015/05",
            "year": "2015",
            "month": "05",
            "geeklist_item_link": "https://boardgamegeek.com/geeklist/190679/item/3894798#item3894798",
            "geeklist_host": "reverendunclebastard",
            "contributor": "repairmanjack"
        },
        {
            "geeklist_id": "194479",
            "geeklist_item_id": "4084797",
            "year_month": "2015/08",
            "year": "2015",
            "month": "08",
            "geeklist_item_link": "https://boardgamegeek.com/geeklist/194479/item/4084797#item4084797",
            "geeklist_host": "Iz Nibz",
            "contributor": "eastwoodk"
        },
        {
            "geeklist_id": "198923",
            "geeklist_item_id": "4280546",
            "year_month": "2015/11",
            "year": "2015",
            "month": "11",
            "geeklist_item_link": "https://boardgamegeek.com/geeklist/198923/item/4280546#item4280546",
            "geeklist_host": "rangerx",
            "contributor": "koinskyz"
        },
        {
            "geeklist_id": "200203",
            "geeklist_item_id": "4308492",
            "year_month": "2015/12",
            "year": "2015",
            "month": "12",
            "geeklist_item_link": "https://boardgamegeek.com/geeklist/200203/item/4308492#item4308492",
            "geeklist_host": "mikolajl",
            "contributor": "Ibbo"
        },
        {
            "geeklist_id": "200203",
            "geeklist_item_id": "4314433",
            "year_month": "2015/12",
            "year": "2015",
            "month": "12",
            "geeklist_item_link": "https://boardgamegeek.com/geeklist/200203/item/4314433#item4314433",
            "geeklist_host": "mikolajl",
            "contributor": "permagoof"
        },
        {
            "geeklist_id": "200203",
            "geeklist_item_id": "4345960",
            "year_month": "2015/12",
            "year": "2015",
            "month": "12",
            "geeklist_item_link": "https://boardgamegeek.com/geeklist/200203/item/4345960#item4345960",
            "geeklist_host": "mikolajl",
            "contributor": "repairmanjack"
        },
        {
            "geeklist_id": "200203",
            "geeklist_item_id": "4346704",
            "year_month": "2015/12",
            "year": "2015",
            "month": "12",
            "geeklist_item_link": "https://boardgamegeek.com/geeklist/200203/item/4346704#item4346704",
            "geeklist_host": "mikolajl",
            "contributor": "repairmanjack"
        },
        {
            "geeklist_id": "204546",
            "geeklist_item_id": "4430169",
            "year_month": "2016/02",
            "year": "2016",
            "month": "02",
            "geeklist_item_link": "https://boardgamegeek.com/geeklist/204546/item/4430169#item4430169",
            "geeklist_host": "Woelf",
            "contributor": "uniconfis"
        },
        {
            "geeklist_id": "204546",
            "geeklist_item_id": "4455966",
            "year_month": "2016/02",
            "year": "2016",
            "month": "02",
            "geeklist_item_link": "https://boardgamegeek.com/geeklist/204546/item/4455966#item4455966",
            "geeklist_host": "Woelf",
            "contributor": "uniconfis"
        },
        {
            "geeklist_id": "205877",
            "geeklist_item_id": "4492609",
            "year_month": "2016/03",
            "year": "2016",
            "month": "03",
            "geeklist_item_link": "https://boardgamegeek.com/geeklist/205877/item/4492609#item4492609",
            "geeklist_host": "pusherman42",
            "contributor": "Pojopep"
        },
        {
            "geeklist_id": "208306",
            "geeklist_item_id": "4628422",
            "year_month": "2016/05",
            "year": "2016",
            "month": "05",
            "geeklist_item_link": "https://boardgamegeek.com/geeklist/208306/item/4628422#item4628422",
            "geeklist_host": "gentle",
            "contributor": "Ibbo"
        },
        {
            "geeklist_id": "210694",
            "geeklist_item_id": "4764557",
            "year_month": "2016/07",
            "year": "2016",
            "month": "07",
            "geeklist_item_link": "https://boardgamegeek.com/geeklist/210694/item/4764557#item4764557",
            "geeklist_host": "ian_07720169619",
            "contributor": "AbsZero"
        },
        {
            "geeklist_id": "211592",
            "geeklist_item_id": "4771593",
            "year_month": "2016/08",
            "year": "2016",
            "month": "08",
            "geeklist_item_link": "https://boardgamegeek.com/geeklist/211592/item/4771593#item4771593",
            "geeklist_host": "govmiller",
            "contributor": "AbsZero"
        },
        {
            "geeklist_id": "211592",
            "geeklist_item_id": "4784530",
            "year_month": "2016/08",
            "year": "2016",
            "month": "08",
            "geeklist_item_link": "https://boardgamegeek.com/geeklist/211592/item/4784530#item4784530",
            "geeklist_host": "govmiller",
            "contributor": "koinskyz"
        },
        {
            "geeklist_id": "211592",
            "geeklist_item_id": "4785393",
            "year_month": "2016/08",
            "year": "2016",
            "month": "08",
            "geeklist_item_link": "https://boardgamegeek.com/geeklist/211592/item/4785393#item4785393",
            "geeklist_host": "govmiller",
            "contributor": "AbsZero"
        },
        {
            "geeklist_id": "211592",
            "geeklist_item_id": "4818908",
            "year_month": "2016/08",
            "year": "2016",
            "month": "08",
            "geeklist_item_link": "https://boardgamegeek.com/geeklist/211592/item/4818908#item4818908",
            "geeklist_host": "govmiller",
            "contributor": "Phate999"
        },
        {
            "geeklist_id": "215297",
            "geeklist_item_id": "5040933",
            "year_month": "2016/11",
            "year": "2016",
            "month": "11",
            "geeklist_item_link": "https://boardgamegeek.com/geeklist/215297/item/5040933#item5040933",
            "geeklist_host": "garyrbrooks",
            "contributor": "Ibbo"
        },
        {
            "geeklist_id": "217780",
            "geeklist_item_id": "5078100",
            "year_month": "2016/12",
            "year": "2016",
            "month": "12",
            "geeklist_item_link": "https://boardgamegeek.com/geeklist/217780/item/5078100#item5078100",
            "geeklist_host": "mikolajl",
            "contributor": "Phate999"
        },
        {
            "geeklist_id": "217780",
            "geeklist_item_id": "5081302",
            "year_month": "2016/12",
            "year": "2016",
            "month": "12",
            "geeklist_item_link": "https://boardgamegeek.com/geeklist/217780/item/5081302#item5081302",
            "geeklist_host": "mikolajl",
            "contributor": "Phate999"
        },
        {
            "geeklist_id": "221242",
            "geeklist_item_id": "5228272",
            "year_month": "2017/02",
            "year": "2017",
            "month": "02",
            "geeklist_item_link": "https://boardgamegeek.com/geeklist/221242/item/5228272#item5228272",
            "geeklist_host": "Ibbo",
            "contributor": "cdarlage"
        },
        {
            "geeklist_id": "223927",
            "geeklist_item_id": "5368860",
            "year_month": "2017/05",
            "year": "2017",
            "month": "05",
            "geeklist_item_link": "https://boardgamegeek.com/geeklist/223927/item/5368860#item5368860",
            "geeklist_host": "maloma",
            "contributor": "freudianslip27"
        },
        {
            "geeklist_id": "223927",
            "geeklist_item_id": "5394134",
            "year_month": "2017/05",
            "year": "2017",
            "month": "05",
            "geeklist_item_link": "https://boardgamegeek.com/geeklist/223927/item/5394134#item5394134",
            "geeklist_host": "maloma",
            "contributor": "abendoso"
        },
        {
            "geeklist_id": "223927",
            "geeklist_item_id": "5395778",
            "year_month": "2017/05",
            "year": "2017",
            "month": "05",
            "geeklist_item_link": "https://boardgamegeek.com/geeklist/223927/item/5395778#item5395778",
            "geeklist_host": "maloma",
            "contributor": "abendoso"
        },
        {
            "geeklist_id": "228234",
            "geeklist_item_id": "5586643",
            "year_month": "2017/08",
            "year": "2017",
            "month": "08",
            "geeklist_item_link": "https://boardgamegeek.com/geeklist/228234/item/5586643#item5586643",
            "geeklist_host": "kevinruns262",
            "contributor": "Themackern"
        },
        {
            "geeklist_id": "235012",
            "geeklist_item_id": "5911372",
            "year_month": "2018/01",
            "year": "2018",
            "month": "01",
            "geeklist_item_link": "https://boardgamegeek.com/geeklist/235012/item/5911372#item5911372",
            "geeklist_host": "Jorune",
            "contributor": "Albia"
        },
        {
            "geeklist_id": "238369",
            "geeklist_item_id": "6104689",
            "year_month": "2018/04",
            "year": "2018",
            "month": "04",
            "geeklist_item_link": "https://boardgamegeek.com/geeklist/238369/item/6104689#item6104689",
            "geeklist_host": "skeletonhat",
            "contributor": "Albia"
        },
        {
            "geeklist_id": "241528",
            "geeklist_item_id": "6316136",
            "year_month": "2018/08",
            "year": "2018",
            "month": "08",
            "geeklist_item_link": "https://boardgamegeek.com/geeklist/241528/item/6316136#item6316136",
            "geeklist_host": "spaceman23",
            "contributor": "BrokenAxe"
        },
        {
            "geeklist_id": "241528",
            "geeklist_item_id": "6318244",
            "year_month": "2018/08",
            "year": "2018",
            "month": "08",
            "geeklist_item_link": "https://boardgamegeek.com/geeklist/241528/item/6318244#item6318244",
            "geeklist_host": "spaceman23",
            "contributor": "BrokenAxe"
        },
        {
            "geeklist_id": "241528",
            "geeklist_item_id": "6325838",
            "year_month": "2018/08",
            "year": "2018",
            "month": "08",
            "geeklist_item_link": "https://boardgamegeek.com/geeklist/241528/item/6325838#item6325838",
            "geeklist_host": "spaceman23",
            "contributor": "BrokenAxe"
        },
        {
            "geeklist_id": "241745",
            "geeklist_item_id": "6210999",
            "year_month": "2018/06",
            "year": "2018",
            "month": "06",
            "geeklist_item_link": "https://boardgamegeek.com/geeklist/241745/item/6210999#item6210999",
            "geeklist_host": "Gribbon",
            "contributor": "Albia"
        },
        {
            "geeklist_id": "242306",
            "geeklist_item_id": "6269086",
            "year_month": "2018/07",
            "year": "2018",
            "month": "07",
            "geeklist_item_link": "https://boardgamegeek.com/geeklist/242306/item/6269086#item6269086",
            "geeklist_host": "emodiu5",
            "contributor": "wcordewiner"
        },
        {
            "geeklist_id": "242306",
            "geeklist_item_id": "6279602",
            "year_month": "2018/07",
            "year": "2018",
            "month": "07",
            "geeklist_item_link": "https://boardgamegeek.com/geeklist/242306/item/6279602#item6279602",
            "geeklist_host": "emodiu5",
            "contributor": "wcordewiner"
        },
        {
            "geeklist_id": "244471",
            "geeklist_item_id": "6600217",
            "year_month": "2018/12",
            "year": "2018",
            "month": "12",
            "geeklist_item_link": "https://boardgamegeek.com/geeklist/244471/item/6600217#item6600217",
            "geeklist_host": "squarepegsys",
            "contributor": "Albia"
        },
        {
            "geeklist_id": "244471",
            "geeklist_item_id": "6601205",
            "year_month": "2018/12",
            "year": "2018",
            "month": "12",
            "geeklist_item_link": "https://boardgamegeek.com/geeklist/244471/item/6601205#item6601205",
            "geeklist_host": "squarepegsys",
            "contributor": "Albia"
        },
        {
            "geeklist_id": "246401",
            "geeklist_item_id": "6444625",
            "year_month": "2018/10",
            "year": "2018",
            "month": "10",
            "geeklist_item_link": "https://boardgamegeek.com/geeklist/246401/item/6444625#item6444625",
            "geeklist_host": "kevinruns262",
            "contributor": "BrokenAxe"
        },
        {
            "geeklist_id": "246401",
            "geeklist_item_id": "6446353",
            "year_month": "2018/10",
            "year": "2018",
            "month": "10",
            "geeklist_item_link": "https://boardgamegeek.com/geeklist/246401/item/6446353#item6446353",
            "geeklist_host": "kevinruns262",
            "contributor": "BrokenAxe"
        },
        {
            "geeklist_id": "246401",
            "geeklist_item_id": "6456136",
            "year_month": "2018/10",
            "year": "2018",
            "month": "10",
            "geeklist_item_link": "https://boardgamegeek.com/geeklist/246401/item/6456136#item6456136",
            "geeklist_host": "kevinruns262",
            "contributor": "BrokenAxe"
        },
        {
            "geeklist_id": "249922",
            "geeklist_item_id": "6689580",
            "year_month": "2019/01",
            "year": "2019",
            "month": "01",
            "geeklist_item_link": "https://boardgamegeek.com/geeklist/249922/item/6689580#item6689580",
            "geeklist_host": "runaway_meeple",
            "contributor": "eastwoodk"
        },
        {
            "geeklist_id": "251846",
            "geeklist_item_id": "6794139",
            "year_month": "2019/03",
            "year": "2019",
            "month": "03",
            "geeklist_item_link": "https://boardgamegeek.com/geeklist/251846/item/6794139#item6794139",
            "geeklist_host": "Donutz McGoo",
            "contributor": "BrokenAxe"
        },
        {
            "geeklist_id": "255931",
            "geeklist_item_id": "6942503",
            "year_month": "2019/05",
            "year": "2019",
            "month": "05",
            "geeklist_item_link": "https://boardgamegeek.com/geeklist/255931/item/6942503#item6942503",
            "geeklist_host": "Woelf",
            "contributor": "Rorpen86"
        },
        {
            "geeklist_id": "256394",
            "geeklist_item_id": "6999465",
            "year_month": "2019/06",
            "year": "2019",
            "month": "06",
            "geeklist_item_link": "https://boardgamegeek.com/geeklist/256394/item/6999465#item6999465",
            "geeklist_host": "magic_erwt",
            "contributor": "eastwoodk"
        },
        {
            "geeklist_id": "260880",
            "geeklist_item_id": "7146195",
            "year_month": "2019/09",
            "year": "2019",
            "month": "09",
            "geeklist_item_link": "https://boardgamegeek.com/geeklist/260880/item/7146195#item7146195",
            "geeklist_host": "jgatkinsn",
            "contributor": "VincentDarlage"
        },
        {
            "geeklist_id": "262008",
            "geeklist_item_id": "7376365",
            "year_month": "2019/12",
            "year": "2019",
            "month": "12",
            "geeklist_item_link": "https://boardgamegeek.com/geeklist/262008/item/7376365#item7376365",
            "geeklist_host": "jeffrhind",
            "contributor": "TheGrimGopher"
        },
        {
            "geeklist_id": "262319",
            "geeklist_item_id": "7231632",
            "year_month": "2019/10",
            "year": "2019",
            "month": "10",
            "geeklist_item_link": "https://boardgamegeek.com/geeklist/262319/item/7231632#item7231632",
            "geeklist_host": "narcher007",
            "contributor": "TheGrimGopher"
        },
        {
            "geeklist_id": "275246",
            "geeklist_item_id": "7805141",
            "year_month": "2020/08",
            "year": "2020",
            "month": "08",
            "geeklist_item_link": "https://boardgamegeek.com/geeklist/275246/item/7805141#item7805141",
            "geeklist_host": "mithoron",
            "contributor": "MadMihi"
        },
        {
            "geeklist_id": "278237",
            "geeklist_item_id": "7981260",
            "year_month": "2020/11",
            "year": "2020",
            "month": "11",
            "geeklist_item_link": "https://boardgamegeek.com/geeklist/278237/item/7981260#item7981260",
            "geeklist_host": "Albia",
            "contributor": "Iz Nibz"
        }
    ],
    "sgoyt_count_174241": 1,
    "sgoyt_count_178257": 1,
    "sgoyt_count_179645": 2,
    "sgoyt_count_182573": 1,
    "sgoyt_count_183994": 3,
    "sgoyt_count_186058": 3,
    "sgoyt_count_190679": 2,
    "sgoyt_count_194479": 1,
    "sgoyt_count_198923": 1,
    "sgoyt_count_200203": 4,
    "sgoyt_count_204546": 2,
    "sgoyt_count_205877": 1,
    "sgoyt_count_208306": 1,
    "sgoyt_count_210694": 1,
    "sgoyt_count_211592": 4,
    "sgoyt_count_215297": 1,
    "sgoyt_count_217780": 2,
    "sgoyt_count_221242": 1,
    "sgoyt_count_223927": 3,
    "sgoyt_count_228234": 1,
    "sgoyt_count_235012": 1,
    "sgoyt_count_238369": 1,
    "sgoyt_count_241528": 3,
    "sgoyt_count_241745": 1,
    "sgoyt_count_242306": 2,
    "sgoyt_count_244471": 2,
    "sgoyt_count_246401": 3,
    "sgoyt_count_249922": 1,
    "sgoyt_count_251846": 1,
    "sgoyt_count_255931": 1,
    "sgoyt_count_256394": 1,
    "sgoyt_count_260880": 1,
    "sgoyt_count_262008": 1,
    "sgoyt_count_262319": 1,
    "sgoyt_count_275246": 1,
    "sgoyt_count_278237": 1,
    "sgoyt_count_156765": 0,
    "sgoyt_count_157888": 0,
    "sgoyt_count_158763": 0,
    "sgoyt_count_160445": 0,
    "sgoyt_count_161764": 0,
    "sgoyt_count_163198": 0,
    "sgoyt_count_164593": 0,
    "sgoyt_count_166060": 0,
    "sgoyt_count_169311": 0,
    "sgoyt_count_170533": 0,
    "sgoyt_count_171598": 0,
    "sgoyt_count_172996": 0,
    "sgoyt_count_175551": 0,
    "sgoyt_count_176697": 0,
    "sgoyt_count_178963": 0,
    "sgoyt_count_182515": 0,
    "sgoyt_count_186592": 0,
    "sgoyt_count_191963": 0,
    "sgoyt_count_193005": 0,
    "sgoyt_count_194940": 0,
    "sgoyt_count_197513": 0,
    "sgoyt_count_202271": 0,
    "sgoyt_count_206595": 0,
    "sgoyt_count_209493": 0,
    "sgoyt_count_213557": 0,
    "sgoyt_count_214406": 0,
    "sgoyt_count_219163": 0,
    "sgoyt_count_222478": 0,
    "sgoyt_count_223793": 0,
    "sgoyt_count_225998": 0,
    "sgoyt_count_227011": 0,
    "sgoyt_count_229124": 0,
    "sgoyt_count_229952": 0,
    "sgoyt_count_231127": 0,
    "sgoyt_count_233358": 0,
    "sgoyt_count_237172": 0,
    "sgoyt_count_238328": 0,
    "sgoyt_count_240624": 0,
    "sgoyt_count_245355": 0,
    "sgoyt_count_247302": 0,
    "sgoyt_count_251880": 0,
    "sgoyt_count_252324": 0,
    "sgoyt_count_253515": 0,
    "sgoyt_count_258026": 0,
    "sgoyt_count_262633": 0,
    "sgoyt_count_266487": 0,
    "sgoyt_count_268583": 0,
    "sgoyt_count_269654": 0,
    "sgoyt_count_270349": 0,
    "sgoyt_count_272126": 0,
    "sgoyt_count_273040": 0,
    "sgoyt_count_274323": 0,
    "sgoyt_count_276177": 0,
    "sgoyt_count_277289": 0,
    "sgoyt_count_279491": 0,
    "sgoyt_count_280864": 0,
    "sgoyt_count_281198": 0,
    "sgoyt_count_282453": 0,
    "sgoyt_count_284335": 0,
    "sgoyt_count_285147": 0,
    "sgoyt_count_285399": 0,
    "sgoyt_count": 58,
    "thumbnail": "https://cf.geekdo-images.com/J2jv3Litm8sy9sVZRI_8Eg__thumb/img/BkB7P6Ruhf0fr6OjFDxlGfUuuAc=/fit-in/200x150/filters:strip_icc()/pic1608871.jpg",
    "year_published": "2013",
    "designers": [
        "Josh J. Carlson",
        "Adam Carlson"
    ],
    "weight": 2.94,
    "rating": 8.19,
    "play_time": "30",
    "best": "5",
    "recommended": "2",
    "not_recommended": "0",
    "categories": [
        "Dice",
        "Fighting"
    ],
    "mechanics": [
        "Cooperative Game",
        "Deck, Bag, and Pool Building",
        "Dice Rolling",
        "Enclosure",
        "Hand Management",
        "Hexagon Grid",
        "Solo / Solitaire Game"
    ],
    "expansions": [
        {
            "expansion_id": "195520",
            "expansion_name": "Hoplomachus: Army of One",
            "expansion_bgg_link": "https://boardgamegeek.com/boardgame/195520"
        },
        {
            "expansion_id": "154587",
            "expansion_name": "Hoplomachus: Beast & Master",
            "expansion_bgg_link": "https://boardgamegeek.com/boardgame/154587"
        },
        {
            "expansion_id": "141412",
            "expansion_name": "Hoplomachus: Blade's Edge",
            "expansion_bgg_link": "https://boardgamegeek.com/boardgame/141412"
        },
        {
            "expansion_id": "234899",
            "expansion_name": "Hoplomachus: Carthage",
            "expansion_bgg_link": "https://boardgamegeek.com/boardgame/234899"
        },
        {
            "expansion_id": "176900",
            "expansion_name": "Hoplomachus: Crowd Favor Gladiator Promo Chips",
            "expansion_bgg_link": "https://boardgamegeek.com/boardgame/176900"
        },
        {
            "expansion_id": "176780",
            "expansion_name": "Hoplomachus: Crowd Favor Gladiators - BGG Promo Pack 1",
            "expansion_bgg_link": "https://boardgamegeek.com/boardgame/176780"
        },
        {
            "expansion_id": "262318",
            "expansion_name": "Hoplomachus: Crowd Favor Gladiators - BGG Promo Pack 2",
            "expansion_bgg_link": "https://boardgamegeek.com/boardgame/262318"
        },
        {
            "expansion_id": "262319",
            "expansion_name": "Hoplomachus: Crowd Favor Gladiators - BGG Promo Pack 3",
            "expansion_bgg_link": "https://boardgamegeek.com/boardgame/262319"
        },
        {
            "expansion_id": "248766",
            "expansion_name": "Hoplomachus: FaMel Ruins Arena",
            "expansion_bgg_link": "https://boardgamegeek.com/boardgame/248766"
        },
        {
            "expansion_id": "200265",
            "expansion_name": "Hoplomachus: Golden Tribute",
            "expansion_bgg_link": "https://boardgamegeek.com/boardgame/200265"
        },
        {
            "expansion_id": "141413",
            "expansion_name": "Hoplomachus: Legends of the Sand",
            "expansion_bgg_link": "https://boardgamegeek.com/boardgame/141413"
        },
        {
            "expansion_id": "234898",
            "expansion_name": "Hoplomachus: Machu Picchu",
            "expansion_bgg_link": "https://boardgamegeek.com/boardgame/234898"
        },
        {
            "expansion_id": "200264",
            "expansion_name": "Hoplomachus: Paying Homage",
            "expansion_bgg_link": "https://boardgamegeek.com/boardgame/200264"
        }
    ],
    "expansion_for": [],
    "designers_string": "Josh J. Carlson; Adam Carlson",
    "categories_string": "Dice; Fighting",
    "mechanics_string": "Cooperative Game; Deck, Bag, and Pool Building; Dice Rolling; Enclosure; Hand Management; Hexagon Grid; Solo / Solitaire Game",
    "expansions_string": "{'expansion_id': '195520', 'expansion_name': 'Hoplomachus: Army of One', 'expansion_bgg_link': 'https://boardgamegeek.com/boardgame/195520'}; {'expansion_id': '154587', 'expansion_name': 'Hoplomachus: Beast & Master', 'expansion_bgg_link': 'https://boardgamegeek.com/boardgame/154587'}; {'expansion_id': '141412', 'expansion_name': \"Hoplomachus: Blade's Edge\", 'expansion_bgg_link': 'https://boardgamegeek.com/boardgame/141412'}; {'expansion_id': '234899', 'expansion_name': 'Hoplomachus: Carthage', 'expansion_bgg_link': 'https://boardgamegeek.com/boardgame/234899'}; {'expansion_id': '176900', 'expansion_name': 'Hoplomachus: Crowd Favor Gladiator Promo Chips', 'expansion_bgg_link': 'https://boardgamegeek.com/boardgame/176900'}; {'expansion_id': '176780', 'expansion_name': 'Hoplomachus: Crowd Favor Gladiators - BGG Promo Pack 1', 'expansion_bgg_link': 'https://boardgamegeek.com/boardgame/176780'}; {'expansion_id': '262318', 'expansion_name': 'Hoplomachus: Crowd Favor Gladiators - BGG Promo Pack 2', 'expansion_bgg_link': 'https://boardgamegeek.com/boardgame/262318'}; {'expansion_id': '262319', 'expansion_name': 'Hoplomachus: Crowd Favor Gladiators - BGG Promo Pack 3', 'expansion_bgg_link': 'https://boardgamegeek.com/boardgame/262319'}; {'expansion_id': '248766', 'expansion_name': 'Hoplomachus: FaMel Ruins Arena', 'expansion_bgg_link': 'https://boardgamegeek.com/boardgame/248766'}; {'expansion_id': '200265', 'expansion_name': 'Hoplomachus: Golden Tribute', 'expansion_bgg_link': 'https://boardgamegeek.com/boardgame/200265'}; {'expansion_id': '141413', 'expansion_name': 'Hoplomachus: Legends of the Sand', 'expansion_bgg_link': 'https://boardgamegeek.com/boardgame/141413'}; {'expansion_id': '234898', 'expansion_name': 'Hoplomachus: Machu Picchu', 'expansion_bgg_link': 'https://boardgamegeek.com/boardgame/234898'}; {'expansion_id': '200264', 'expansion_name': 'Hoplomachus: Paying Homage', 'expansion_bgg_link': 'https://boardgamegeek.com/boardgame/200264'}",
    "expansions_for_string": ""
}