{
    "game_id": "164874",
    "game_name": "Airborne Commander",
    "bgg_link": "https://boardgamegeek.com/boardgame/164874",
    "sgoyt_entries": [
        {
            "geeklist_id": "178963",
            "geeklist_item_id": "3510158",
            "year_month": "2014/10",
            "year": "2014",
            "month": "10",
            "geeklist_item_link": "https://boardgamegeek.com/geeklist/178963/item/3510158#item3510158",
            "geeklist_host": "joestin",
            "contributor": "Arrakhan"
        },
        {
            "geeklist_id": "178963",
            "geeklist_item_id": "3512180",
            "year_month": "2014/10",
            "year": "2014",
            "month": "10",
            "geeklist_item_link": "https://boardgamegeek.com/geeklist/178963/item/3512180#item3512180",
            "geeklist_host": "joestin",
            "contributor": "jacobjcoon"
        },
        {
            "geeklist_id": "182515",
            "geeklist_item_id": "3804366",
            "year_month": "2015/03",
            "year": "2015",
            "month": "03",
            "geeklist_item_link": "https://boardgamegeek.com/geeklist/182515/item/3804366#item3804366",
            "geeklist_host": "HRune",
            "contributor": "Turbine2k5"
        },
        {
            "geeklist_id": "183994",
            "geeklist_item_id": "3673326",
            "year_month": "2015/01",
            "year": "2015",
            "month": "01",
            "geeklist_item_link": "https://boardgamegeek.com/geeklist/183994/item/3673326#item3673326",
            "geeklist_host": "bikefreak",
            "contributor": "Arrakhan"
        },
        {
            "geeklist_id": "198923",
            "geeklist_item_id": "4286727",
            "year_month": "2015/11",
            "year": "2015",
            "month": "11",
            "geeklist_item_link": "https://boardgamegeek.com/geeklist/198923/item/4286727#item4286727",
            "geeklist_host": "rangerx",
            "contributor": "NewbieGamingDad"
        },
        {
            "geeklist_id": "198923",
            "geeklist_item_id": "4287467",
            "year_month": "2015/11",
            "year": "2015",
            "month": "11",
            "geeklist_item_link": "https://boardgamegeek.com/geeklist/198923/item/4287467#item4287467",
            "geeklist_host": "rangerx",
            "contributor": "joestin"
        },
        {
            "geeklist_id": "200203",
            "geeklist_item_id": "4307075",
            "year_month": "2015/12",
            "year": "2015",
            "month": "12",
            "geeklist_item_link": "https://boardgamegeek.com/geeklist/200203/item/4307075#item4307075",
            "geeklist_host": "mikolajl",
            "contributor": "SBGrad"
        },
        {
            "geeklist_id": "200203",
            "geeklist_item_id": "4310577",
            "year_month": "2015/12",
            "year": "2015",
            "month": "12",
            "geeklist_item_link": "https://boardgamegeek.com/geeklist/200203/item/4310577#item4310577",
            "geeklist_host": "mikolajl",
            "contributor": "richdodgin"
        },
        {
            "geeklist_id": "200203",
            "geeklist_item_id": "4316435",
            "year_month": "2015/12",
            "year": "2015",
            "month": "12",
            "geeklist_item_link": "https://boardgamegeek.com/geeklist/200203/item/4316435#item4316435",
            "geeklist_host": "mikolajl",
            "contributor": "seanmac"
        },
        {
            "geeklist_id": "200203",
            "geeklist_item_id": "4318799",
            "year_month": "2015/12",
            "year": "2015",
            "month": "12",
            "geeklist_item_link": "https://boardgamegeek.com/geeklist/200203/item/4318799#item4318799",
            "geeklist_host": "mikolajl",
            "contributor": "airjudden"
        },
        {
            "geeklist_id": "200203",
            "geeklist_item_id": "4323438",
            "year_month": "2015/12",
            "year": "2015",
            "month": "12",
            "geeklist_item_link": "https://boardgamegeek.com/geeklist/200203/item/4323438#item4323438",
            "geeklist_host": "mikolajl",
            "contributor": "gentle"
        },
        {
            "geeklist_id": "200203",
            "geeklist_item_id": "4324357",
            "year_month": "2015/12",
            "year": "2015",
            "month": "12",
            "geeklist_item_link": "https://boardgamegeek.com/geeklist/200203/item/4324357#item4324357",
            "geeklist_host": "mikolajl",
            "contributor": "Lunga"
        },
        {
            "geeklist_id": "200203",
            "geeklist_item_id": "4327099",
            "year_month": "2015/12",
            "year": "2015",
            "month": "12",
            "geeklist_item_link": "https://boardgamegeek.com/geeklist/200203/item/4327099#item4327099",
            "geeklist_host": "mikolajl",
            "contributor": "Lunga"
        },
        {
            "geeklist_id": "200203",
            "geeklist_item_id": "4327182",
            "year_month": "2015/12",
            "year": "2015",
            "month": "12",
            "geeklist_item_link": "https://boardgamegeek.com/geeklist/200203/item/4327182#item4327182",
            "geeklist_host": "mikolajl",
            "contributor": "kittenhoarder"
        },
        {
            "geeklist_id": "200203",
            "geeklist_item_id": "4328693",
            "year_month": "2015/12",
            "year": "2015",
            "month": "12",
            "geeklist_item_link": "https://boardgamegeek.com/geeklist/200203/item/4328693#item4328693",
            "geeklist_host": "mikolajl",
            "contributor": "kittenhoarder"
        },
        {
            "geeklist_id": "200203",
            "geeklist_item_id": "4330807",
            "year_month": "2015/12",
            "year": "2015",
            "month": "12",
            "geeklist_item_link": "https://boardgamegeek.com/geeklist/200203/item/4330807#item4330807",
            "geeklist_host": "mikolajl",
            "contributor": "gentle"
        },
        {
            "geeklist_id": "200203",
            "geeklist_item_id": "4333846",
            "year_month": "2015/12",
            "year": "2015",
            "month": "12",
            "geeklist_item_link": "https://boardgamegeek.com/geeklist/200203/item/4333846#item4333846",
            "geeklist_host": "mikolajl",
            "contributor": "Lunga"
        },
        {
            "geeklist_id": "200203",
            "geeklist_item_id": "4340041",
            "year_month": "2015/12",
            "year": "2015",
            "month": "12",
            "geeklist_item_link": "https://boardgamegeek.com/geeklist/200203/item/4340041#item4340041",
            "geeklist_host": "mikolajl",
            "contributor": "kittenhoarder"
        },
        {
            "geeklist_id": "202271",
            "geeklist_item_id": "4361836",
            "year_month": "2016/01",
            "year": "2016",
            "month": "01",
            "geeklist_item_link": "https://boardgamegeek.com/geeklist/202271/item/4361836#item4361836",
            "geeklist_host": "suzyvitale",
            "contributor": "Lunga"
        },
        {
            "geeklist_id": "202271",
            "geeklist_item_id": "4367921",
            "year_month": "2016/01",
            "year": "2016",
            "month": "01",
            "geeklist_item_link": "https://boardgamegeek.com/geeklist/202271/item/4367921#item4367921",
            "geeklist_host": "suzyvitale",
            "contributor": "SBGrad"
        },
        {
            "geeklist_id": "202271",
            "geeklist_item_id": "4427109",
            "year_month": "2016/01",
            "year": "2016",
            "month": "01",
            "geeklist_item_link": "https://boardgamegeek.com/geeklist/202271/item/4427109#item4427109",
            "geeklist_host": "suzyvitale",
            "contributor": "gentle"
        },
        {
            "geeklist_id": "204546",
            "geeklist_item_id": "4430994",
            "year_month": "2016/02",
            "year": "2016",
            "month": "02",
            "geeklist_item_link": "https://boardgamegeek.com/geeklist/204546/item/4430994#item4430994",
            "geeklist_host": "Woelf",
            "contributor": "SBGrad"
        },
        {
            "geeklist_id": "204546",
            "geeklist_item_id": "4442786",
            "year_month": "2016/02",
            "year": "2016",
            "month": "02",
            "geeklist_item_link": "https://boardgamegeek.com/geeklist/204546/item/4442786#item4442786",
            "geeklist_host": "Woelf",
            "contributor": "lukather"
        },
        {
            "geeklist_id": "204546",
            "geeklist_item_id": "4444738",
            "year_month": "2016/02",
            "year": "2016",
            "month": "02",
            "geeklist_item_link": "https://boardgamegeek.com/geeklist/204546/item/4444738#item4444738",
            "geeklist_host": "Woelf",
            "contributor": "garyrbrooks"
        },
        {
            "geeklist_id": "204546",
            "geeklist_item_id": "4458268",
            "year_month": "2016/02",
            "year": "2016",
            "month": "02",
            "geeklist_item_link": "https://boardgamegeek.com/geeklist/204546/item/4458268#item4458268",
            "geeklist_host": "Woelf",
            "contributor": "repairmanjack"
        },
        {
            "geeklist_id": "204546",
            "geeklist_item_id": "4459428",
            "year_month": "2016/02",
            "year": "2016",
            "month": "02",
            "geeklist_item_link": "https://boardgamegeek.com/geeklist/204546/item/4459428#item4459428",
            "geeklist_host": "Woelf",
            "contributor": "repairmanjack"
        },
        {
            "geeklist_id": "204546",
            "geeklist_item_id": "4472092",
            "year_month": "2016/02",
            "year": "2016",
            "month": "02",
            "geeklist_item_link": "https://boardgamegeek.com/geeklist/204546/item/4472092#item4472092",
            "geeklist_host": "Woelf",
            "contributor": "repairmanjack"
        },
        {
            "geeklist_id": "204546",
            "geeklist_item_id": "4473481",
            "year_month": "2016/02",
            "year": "2016",
            "month": "02",
            "geeklist_item_link": "https://boardgamegeek.com/geeklist/204546/item/4473481#item4473481",
            "geeklist_host": "Woelf",
            "contributor": "Lunga"
        },
        {
            "geeklist_id": "205877",
            "geeklist_item_id": "4507565",
            "year_month": "2016/03",
            "year": "2016",
            "month": "03",
            "geeklist_item_link": "https://boardgamegeek.com/geeklist/205877/item/4507565#item4507565",
            "geeklist_host": "pusherman42",
            "contributor": "SPI Mark"
        },
        {
            "geeklist_id": "205877",
            "geeklist_item_id": "4509976",
            "year_month": "2016/03",
            "year": "2016",
            "month": "03",
            "geeklist_item_link": "https://boardgamegeek.com/geeklist/205877/item/4509976#item4509976",
            "geeklist_host": "pusherman42",
            "contributor": "eastwoodk"
        },
        {
            "geeklist_id": "205877",
            "geeklist_item_id": "4517005",
            "year_month": "2016/03",
            "year": "2016",
            "month": "03",
            "geeklist_item_link": "https://boardgamegeek.com/geeklist/205877/item/4517005#item4517005",
            "geeklist_host": "pusherman42",
            "contributor": "markmorrise"
        },
        {
            "geeklist_id": "205877",
            "geeklist_item_id": "4527128",
            "year_month": "2016/03",
            "year": "2016",
            "month": "03",
            "geeklist_item_link": "https://boardgamegeek.com/geeklist/205877/item/4527128#item4527128",
            "geeklist_host": "pusherman42",
            "contributor": "joestin"
        },
        {
            "geeklist_id": "206595",
            "geeklist_item_id": "4552632",
            "year_month": "2016/04",
            "year": "2016",
            "month": "04",
            "geeklist_item_link": "https://boardgamegeek.com/geeklist/206595/item/4552632#item4552632",
            "geeklist_host": "jdarnold",
            "contributor": "SBGrad"
        },
        {
            "geeklist_id": "206595",
            "geeklist_item_id": "4556724",
            "year_month": "2016/04",
            "year": "2016",
            "month": "04",
            "geeklist_item_link": "https://boardgamegeek.com/geeklist/206595/item/4556724#item4556724",
            "geeklist_host": "jdarnold",
            "contributor": "Huddyrx"
        },
        {
            "geeklist_id": "206595",
            "geeklist_item_id": "4590309",
            "year_month": "2016/04",
            "year": "2016",
            "month": "04",
            "geeklist_item_link": "https://boardgamegeek.com/geeklist/206595/item/4590309#item4590309",
            "geeklist_host": "jdarnold",
            "contributor": "suzyvitale"
        },
        {
            "geeklist_id": "206595",
            "geeklist_item_id": "4591283",
            "year_month": "2016/04",
            "year": "2016",
            "month": "04",
            "geeklist_item_link": "https://boardgamegeek.com/geeklist/206595/item/4591283#item4591283",
            "geeklist_host": "jdarnold",
            "contributor": "suzyvitale"
        },
        {
            "geeklist_id": "208306",
            "geeklist_item_id": "4611727",
            "year_month": "2016/05",
            "year": "2016",
            "month": "05",
            "geeklist_item_link": "https://boardgamegeek.com/geeklist/208306/item/4611727#item4611727",
            "geeklist_host": "gentle",
            "contributor": "SBGrad"
        },
        {
            "geeklist_id": "208306",
            "geeklist_item_id": "4655253",
            "year_month": "2016/05",
            "year": "2016",
            "month": "05",
            "geeklist_item_link": "https://boardgamegeek.com/geeklist/208306/item/4655253#item4655253",
            "geeklist_host": "gentle",
            "contributor": "Tokhuah"
        },
        {
            "geeklist_id": "209493",
            "geeklist_item_id": "4661947",
            "year_month": "2016/06",
            "year": "2016",
            "month": "06",
            "geeklist_item_link": "https://boardgamegeek.com/geeklist/209493/item/4661947#item4661947",
            "geeklist_host": "koinskyz",
            "contributor": "SBGrad"
        },
        {
            "geeklist_id": "209493",
            "geeklist_item_id": "4700040",
            "year_month": "2016/06",
            "year": "2016",
            "month": "06",
            "geeklist_item_link": "https://boardgamegeek.com/geeklist/209493/item/4700040#item4700040",
            "geeklist_host": "koinskyz",
            "contributor": "repairmanjack"
        },
        {
            "geeklist_id": "209493",
            "geeklist_item_id": "4705386",
            "year_month": "2016/06",
            "year": "2016",
            "month": "06",
            "geeklist_item_link": "https://boardgamegeek.com/geeklist/209493/item/4705386#item4705386",
            "geeklist_host": "koinskyz",
            "contributor": "Tokhuah"
        },
        {
            "geeklist_id": "210694",
            "geeklist_item_id": "4716698",
            "year_month": "2016/07",
            "year": "2016",
            "month": "07",
            "geeklist_item_link": "https://boardgamegeek.com/geeklist/210694/item/4716698#item4716698",
            "geeklist_host": "ian_07720169619",
            "contributor": "skyzero"
        },
        {
            "geeklist_id": "210694",
            "geeklist_item_id": "4724625",
            "year_month": "2016/07",
            "year": "2016",
            "month": "07",
            "geeklist_item_link": "https://boardgamegeek.com/geeklist/210694/item/4724625#item4724625",
            "geeklist_host": "ian_07720169619",
            "contributor": "eastwoodk"
        },
        {
            "geeklist_id": "210694",
            "geeklist_item_id": "4726330",
            "year_month": "2016/07",
            "year": "2016",
            "month": "07",
            "geeklist_item_link": "https://boardgamegeek.com/geeklist/210694/item/4726330#item4726330",
            "geeklist_host": "ian_07720169619",
            "contributor": "SBGrad"
        },
        {
            "geeklist_id": "211592",
            "geeklist_item_id": "4789855",
            "year_month": "2016/08",
            "year": "2016",
            "month": "08",
            "geeklist_item_link": "https://boardgamegeek.com/geeklist/211592/item/4789855#item4789855",
            "geeklist_host": "govmiller",
            "contributor": "SBGrad"
        },
        {
            "geeklist_id": "211592",
            "geeklist_item_id": "4840139",
            "year_month": "2016/08",
            "year": "2016",
            "month": "08",
            "geeklist_item_link": "https://boardgamegeek.com/geeklist/211592/item/4840139#item4840139",
            "geeklist_host": "govmiller",
            "contributor": "Pjandy"
        },
        {
            "geeklist_id": "213557",
            "geeklist_item_id": "4847717",
            "year_month": "2016/09",
            "year": "2016",
            "month": "09",
            "geeklist_item_link": "https://boardgamegeek.com/geeklist/213557/item/4847717#item4847717",
            "geeklist_host": "kikerl",
            "contributor": "SBGrad"
        },
        {
            "geeklist_id": "213557",
            "geeklist_item_id": "4883309",
            "year_month": "2016/09",
            "year": "2016",
            "month": "09",
            "geeklist_item_link": "https://boardgamegeek.com/geeklist/213557/item/4883309#item4883309",
            "geeklist_host": "kikerl",
            "contributor": "Pjandy"
        },
        {
            "geeklist_id": "213557",
            "geeklist_item_id": "4891456",
            "year_month": "2016/09",
            "year": "2016",
            "month": "09",
            "geeklist_item_link": "https://boardgamegeek.com/geeklist/213557/item/4891456#item4891456",
            "geeklist_host": "kikerl",
            "contributor": "tlyoder57"
        },
        {
            "geeklist_id": "214406",
            "geeklist_item_id": "4985070",
            "year_month": "2016/10",
            "year": "2016",
            "month": "10",
            "geeklist_item_link": "https://boardgamegeek.com/geeklist/214406/item/4985070#item4985070",
            "geeklist_host": "maloma",
            "contributor": "Redheaded Pharmacist"
        },
        {
            "geeklist_id": "214406",
            "geeklist_item_id": "4987508",
            "year_month": "2016/10",
            "year": "2016",
            "month": "10",
            "geeklist_item_link": "https://boardgamegeek.com/geeklist/214406/item/4987508#item4987508",
            "geeklist_host": "maloma",
            "contributor": "Moe45673"
        },
        {
            "geeklist_id": "214406",
            "geeklist_item_id": "4990968",
            "year_month": "2016/10",
            "year": "2016",
            "month": "10",
            "geeklist_item_link": "https://boardgamegeek.com/geeklist/214406/item/4990968#item4990968",
            "geeklist_host": "maloma",
            "contributor": "joestin"
        },
        {
            "geeklist_id": "214406",
            "geeklist_item_id": "4992684",
            "year_month": "2016/10",
            "year": "2016",
            "month": "10",
            "geeklist_item_link": "https://boardgamegeek.com/geeklist/214406/item/4992684#item4992684",
            "geeklist_host": "maloma",
            "contributor": "Moe45673"
        },
        {
            "geeklist_id": "215297",
            "geeklist_item_id": "5032846",
            "year_month": "2016/11",
            "year": "2016",
            "month": "11",
            "geeklist_item_link": "https://boardgamegeek.com/geeklist/215297/item/5032846#item5032846",
            "geeklist_host": "garyrbrooks",
            "contributor": "Redheaded Pharmacist"
        },
        {
            "geeklist_id": "215297",
            "geeklist_item_id": "5034759",
            "year_month": "2016/11",
            "year": "2016",
            "month": "11",
            "geeklist_item_link": "https://boardgamegeek.com/geeklist/215297/item/5034759#item5034759",
            "geeklist_host": "garyrbrooks",
            "contributor": "Moe45673"
        },
        {
            "geeklist_id": "217780",
            "geeklist_item_id": "5078142",
            "year_month": "2016/12",
            "year": "2016",
            "month": "12",
            "geeklist_item_link": "https://boardgamegeek.com/geeklist/217780/item/5078142#item5078142",
            "geeklist_host": "mikolajl",
            "contributor": "TheStoicEmperor"
        },
        {
            "geeklist_id": "219163",
            "geeklist_item_id": "5141581",
            "year_month": "2017/01",
            "year": "2017",
            "month": "01",
            "geeklist_item_link": "https://boardgamegeek.com/geeklist/219163/item/5141581#item5141581",
            "geeklist_host": "settlerdave",
            "contributor": "SBGrad"
        },
        {
            "geeklist_id": "219163",
            "geeklist_item_id": "5175672",
            "year_month": "2017/01",
            "year": "2017",
            "month": "01",
            "geeklist_item_link": "https://boardgamegeek.com/geeklist/219163/item/5175672#item5175672",
            "geeklist_host": "settlerdave",
            "contributor": "vikinggeek"
        },
        {
            "geeklist_id": "219163",
            "geeklist_item_id": "5180644",
            "year_month": "2017/01",
            "year": "2017",
            "month": "01",
            "geeklist_item_link": "https://boardgamegeek.com/geeklist/219163/item/5180644#item5180644",
            "geeklist_host": "settlerdave",
            "contributor": "repairmanjack"
        },
        {
            "geeklist_id": "219163",
            "geeklist_item_id": "5182731",
            "year_month": "2017/01",
            "year": "2017",
            "month": "01",
            "geeklist_item_link": "https://boardgamegeek.com/geeklist/219163/item/5182731#item5182731",
            "geeklist_host": "settlerdave",
            "contributor": "AndrePOR"
        },
        {
            "geeklist_id": "221242",
            "geeklist_item_id": "5205492",
            "year_month": "2017/02",
            "year": "2017",
            "month": "02",
            "geeklist_item_link": "https://boardgamegeek.com/geeklist/221242/item/5205492#item5205492",
            "geeklist_host": "Ibbo",
            "contributor": "SBGrad"
        },
        {
            "geeklist_id": "221242",
            "geeklist_item_id": "5234867",
            "year_month": "2017/02",
            "year": "2017",
            "month": "02",
            "geeklist_item_link": "https://boardgamegeek.com/geeklist/221242/item/5234867#item5234867",
            "geeklist_host": "Ibbo",
            "contributor": "Moe45673"
        },
        {
            "geeklist_id": "221242",
            "geeklist_item_id": "5244323",
            "year_month": "2017/02",
            "year": "2017",
            "month": "02",
            "geeklist_item_link": "https://boardgamegeek.com/geeklist/221242/item/5244323#item5244323",
            "geeklist_host": "Ibbo",
            "contributor": "Rabidkiwi143"
        },
        {
            "geeklist_id": "222478",
            "geeklist_item_id": "5288059",
            "year_month": "2017/03",
            "year": "2017",
            "month": "03",
            "geeklist_item_link": "https://boardgamegeek.com/geeklist/222478/item/5288059#item5288059",
            "geeklist_host": "suzyvitale",
            "contributor": "kevinruns262"
        },
        {
            "geeklist_id": "222478",
            "geeklist_item_id": "5294890",
            "year_month": "2017/03",
            "year": "2017",
            "month": "03",
            "geeklist_item_link": "https://boardgamegeek.com/geeklist/222478/item/5294890#item5294890",
            "geeklist_host": "suzyvitale",
            "contributor": "kevinruns262"
        },
        {
            "geeklist_id": "222478",
            "geeklist_item_id": "5307043",
            "year_month": "2017/03",
            "year": "2017",
            "month": "03",
            "geeklist_item_link": "https://boardgamegeek.com/geeklist/222478/item/5307043#item5307043",
            "geeklist_host": "suzyvitale",
            "contributor": "fee_weasel"
        },
        {
            "geeklist_id": "223927",
            "geeklist_item_id": "5383357",
            "year_month": "2017/05",
            "year": "2017",
            "month": "05",
            "geeklist_item_link": "https://boardgamegeek.com/geeklist/223927/item/5383357#item5383357",
            "geeklist_host": "maloma",
            "contributor": "SBGrad"
        },
        {
            "geeklist_id": "225998",
            "geeklist_item_id": "5442946",
            "year_month": "2017/06",
            "year": "2017",
            "month": "06",
            "geeklist_item_link": "https://boardgamegeek.com/geeklist/225998/item/5442946#item5442946",
            "geeklist_host": "koinskyz",
            "contributor": "kevinruns262"
        },
        {
            "geeklist_id": "225998",
            "geeklist_item_id": "5452116",
            "year_month": "2017/06",
            "year": "2017",
            "month": "06",
            "geeklist_item_link": "https://boardgamegeek.com/geeklist/225998/item/5452116#item5452116",
            "geeklist_host": "koinskyz",
            "contributor": "SBGrad"
        },
        {
            "geeklist_id": "229952",
            "geeklist_item_id": "5730656",
            "year_month": "2017/10",
            "year": "2017",
            "month": "10",
            "geeklist_item_link": "https://boardgamegeek.com/geeklist/229952/item/5730656#item5730656",
            "geeklist_host": "cornishlee",
            "contributor": "mo7189"
        },
        {
            "geeklist_id": "231127",
            "geeklist_item_id": "5762849",
            "year_month": "2017/11",
            "year": "2017",
            "month": "11",
            "geeklist_item_link": "https://boardgamegeek.com/geeklist/231127/item/5762849#item5762849",
            "geeklist_host": "Albia",
            "contributor": "family_gamer"
        },
        {
            "geeklist_id": "235012",
            "geeklist_item_id": "5926856",
            "year_month": "2018/01",
            "year": "2018",
            "month": "01",
            "geeklist_item_link": "https://boardgamegeek.com/geeklist/235012/item/5926856#item5926856",
            "geeklist_host": "Jorune",
            "contributor": "Narrow Gate Games"
        },
        {
            "geeklist_id": "237172",
            "geeklist_item_id": "5961305",
            "year_month": "2018/02",
            "year": "2018",
            "month": "02",
            "geeklist_item_link": "https://boardgamegeek.com/geeklist/237172/item/5961305#item5961305",
            "geeklist_host": "radthanael",
            "contributor": "family_gamer"
        },
        {
            "geeklist_id": "238328",
            "geeklist_item_id": "6054334",
            "year_month": "2018/03",
            "year": "2018",
            "month": "03",
            "geeklist_item_link": "https://boardgamegeek.com/geeklist/238328/item/6054334#item6054334",
            "geeklist_host": "busdjur",
            "contributor": "mo7189"
        },
        {
            "geeklist_id": "238369",
            "geeklist_item_id": "6060367",
            "year_month": "2018/04",
            "year": "2018",
            "month": "04",
            "geeklist_item_link": "https://boardgamegeek.com/geeklist/238369/item/6060367#item6060367",
            "geeklist_host": "skeletonhat",
            "contributor": "Pjandy"
        },
        {
            "geeklist_id": "242306",
            "geeklist_item_id": "6240596",
            "year_month": "2018/07",
            "year": "2018",
            "month": "07",
            "geeklist_item_link": "https://boardgamegeek.com/geeklist/242306/item/6240596#item6240596",
            "geeklist_host": "emodiu5",
            "contributor": "Redheaded Pharmacist"
        },
        {
            "geeklist_id": "249922",
            "geeklist_item_id": "6677055",
            "year_month": "2019/01",
            "year": "2019",
            "month": "01",
            "geeklist_item_link": "https://boardgamegeek.com/geeklist/249922/item/6677055#item6677055",
            "geeklist_host": "runaway_meeple",
            "contributor": "BrokenAxe"
        },
        {
            "geeklist_id": "251846",
            "geeklist_item_id": "6773744",
            "year_month": "2019/03",
            "year": "2019",
            "month": "03",
            "geeklist_item_link": "https://boardgamegeek.com/geeklist/251846/item/6773744#item6773744",
            "geeklist_host": "Donutz McGoo",
            "contributor": "BrokenAxe"
        },
        {
            "geeklist_id": "252324",
            "geeklist_item_id": "6765665",
            "year_month": "2019/02",
            "year": "2019",
            "month": "02",
            "geeklist_item_link": "https://boardgamegeek.com/geeklist/252324/item/6765665#item6765665",
            "geeklist_host": "The_Omnius",
            "contributor": "TheStoicEmperor"
        },
        {
            "geeklist_id": "258026",
            "geeklist_item_id": "7123146",
            "year_month": "2019/08",
            "year": "2019",
            "month": "08",
            "geeklist_item_link": "https://boardgamegeek.com/geeklist/258026/item/7123146#item7123146",
            "geeklist_host": "Venom Snake",
            "contributor": "Pjandy"
        },
        {
            "geeklist_id": "262319",
            "geeklist_item_id": "7284612",
            "year_month": "2019/10",
            "year": "2019",
            "month": "10",
            "geeklist_item_link": "https://boardgamegeek.com/geeklist/262319/item/7284612#item7284612",
            "geeklist_host": "narcher007",
            "contributor": "Redheaded Pharmacist"
        },
        {
            "geeklist_id": "266487",
            "geeklist_item_id": "7446772",
            "year_month": "2020/01",
            "year": "2020",
            "month": "01",
            "geeklist_item_link": "https://boardgamegeek.com/geeklist/266487/item/7446772#item7446772",
            "geeklist_host": "jomurph86",
            "contributor": "Haywood"
        },
        {
            "geeklist_id": "266487",
            "geeklist_item_id": "7493254",
            "year_month": "2020/01",
            "year": "2020",
            "month": "01",
            "geeklist_item_link": "https://boardgamegeek.com/geeklist/266487/item/7493254#item7493254",
            "geeklist_host": "jomurph86",
            "contributor": "airzonk1"
        },
        {
            "geeklist_id": "269654",
            "geeklist_item_id": "7587516",
            "year_month": "2020/03",
            "year": "2020",
            "month": "03",
            "geeklist_item_link": "https://boardgamegeek.com/geeklist/269654/item/7587516#item7587516",
            "geeklist_host": "jwml",
            "contributor": "BrokenAxe"
        },
        {
            "geeklist_id": "269654",
            "geeklist_item_id": "7589705",
            "year_month": "2020/03",
            "year": "2020",
            "month": "03",
            "geeklist_item_link": "https://boardgamegeek.com/geeklist/269654/item/7589705#item7589705",
            "geeklist_host": "jwml",
            "contributor": "BrokenAxe"
        },
        {
            "geeklist_id": "269654",
            "geeklist_item_id": "7602345",
            "year_month": "2020/03",
            "year": "2020",
            "month": "03",
            "geeklist_item_link": "https://boardgamegeek.com/geeklist/269654/item/7602345#item7602345",
            "geeklist_host": "jwml",
            "contributor": "Redheaded Pharmacist"
        },
        {
            "geeklist_id": "273040",
            "geeklist_item_id": "7708130",
            "year_month": "2020/06",
            "year": "2020",
            "month": "06",
            "geeklist_item_link": "https://boardgamegeek.com/geeklist/273040/item/7708130#item7708130",
            "geeklist_host": "Elida",
            "contributor": "Redheaded Pharmacist"
        },
        {
            "geeklist_id": "274323",
            "geeklist_item_id": "7757050",
            "year_month": "2020/07",
            "year": "2020",
            "month": "07",
            "geeklist_item_link": "https://boardgamegeek.com/geeklist/274323/item/7757050#item7757050",
            "geeklist_host": "repairmanjack",
            "contributor": "Redheaded Pharmacist"
        },
        {
            "geeklist_id": "275246",
            "geeklist_item_id": "7800418",
            "year_month": "2020/08",
            "year": "2020",
            "month": "08",
            "geeklist_item_link": "https://boardgamegeek.com/geeklist/275246/item/7800418#item7800418",
            "geeklist_host": "mithoron",
            "contributor": "Redheaded Pharmacist"
        },
        {
            "geeklist_id": "277289",
            "geeklist_item_id": "7936901",
            "year_month": "2020/10",
            "year": "2020",
            "month": "10",
            "geeklist_item_link": "https://boardgamegeek.com/geeklist/277289/item/7936901#item7936901",
            "geeklist_host": "Elida",
            "contributor": "Redheaded Pharmacist"
        },
        {
            "geeklist_id": "278237",
            "geeklist_item_id": "7970438",
            "year_month": "2020/11",
            "year": "2020",
            "month": "11",
            "geeklist_item_link": "https://boardgamegeek.com/geeklist/278237/item/7970438#item7970438",
            "geeklist_host": "Albia",
            "contributor": "Redheaded Pharmacist"
        },
        {
            "geeklist_id": "278237",
            "geeklist_item_id": "7995143",
            "year_month": "2020/11",
            "year": "2020",
            "month": "11",
            "geeklist_item_link": "https://boardgamegeek.com/geeklist/278237/item/7995143#item7995143",
            "geeklist_host": "Albia",
            "contributor": "airjudden"
        },
        {
            "geeklist_id": "280864",
            "geeklist_item_id": "8079751",
            "year_month": "2021/01",
            "year": "2021",
            "month": "01",
            "geeklist_item_link": "https://boardgamegeek.com/geeklist/280864/item/8079751#item8079751",
            "geeklist_host": "Swizze",
            "contributor": "Redheaded Pharmacist"
        },
        {
            "geeklist_id": "281198",
            "geeklist_item_id": "8187973",
            "year_month": "2021/03",
            "year": "2021",
            "month": "03",
            "geeklist_item_link": "https://boardgamegeek.com/geeklist/281198/item/8187973#item8187973",
            "geeklist_host": "montrealmovil",
            "contributor": "landru"
        }
    ],
    "sgoyt_count_178963": 2,
    "sgoyt_count_182515": 1,
    "sgoyt_count_183994": 1,
    "sgoyt_count_198923": 2,
    "sgoyt_count_200203": 12,
    "sgoyt_count_202271": 3,
    "sgoyt_count_204546": 7,
    "sgoyt_count_205877": 4,
    "sgoyt_count_206595": 4,
    "sgoyt_count_208306": 2,
    "sgoyt_count_209493": 3,
    "sgoyt_count_210694": 3,
    "sgoyt_count_211592": 2,
    "sgoyt_count_213557": 3,
    "sgoyt_count_214406": 4,
    "sgoyt_count_215297": 2,
    "sgoyt_count_217780": 1,
    "sgoyt_count_219163": 4,
    "sgoyt_count_221242": 3,
    "sgoyt_count_222478": 3,
    "sgoyt_count_223927": 1,
    "sgoyt_count_225998": 2,
    "sgoyt_count_229952": 1,
    "sgoyt_count_231127": 1,
    "sgoyt_count_235012": 1,
    "sgoyt_count_237172": 1,
    "sgoyt_count_238328": 1,
    "sgoyt_count_238369": 1,
    "sgoyt_count_242306": 1,
    "sgoyt_count_249922": 1,
    "sgoyt_count_251846": 1,
    "sgoyt_count_252324": 1,
    "sgoyt_count_258026": 1,
    "sgoyt_count_262319": 1,
    "sgoyt_count_266487": 2,
    "sgoyt_count_269654": 3,
    "sgoyt_count_273040": 1,
    "sgoyt_count_274323": 1,
    "sgoyt_count_275246": 1,
    "sgoyt_count_277289": 1,
    "sgoyt_count_278237": 2,
    "sgoyt_count_280864": 1,
    "sgoyt_count_281198": 1,
    "sgoyt_count_156765": 0,
    "sgoyt_count_157888": 0,
    "sgoyt_count_158763": 0,
    "sgoyt_count_160445": 0,
    "sgoyt_count_161764": 0,
    "sgoyt_count_163198": 0,
    "sgoyt_count_164593": 0,
    "sgoyt_count_166060": 0,
    "sgoyt_count_169311": 0,
    "sgoyt_count_170533": 0,
    "sgoyt_count_171598": 0,
    "sgoyt_count_172996": 0,
    "sgoyt_count_174241": 0,
    "sgoyt_count_175551": 0,
    "sgoyt_count_176697": 0,
    "sgoyt_count_178257": 0,
    "sgoyt_count_179645": 0,
    "sgoyt_count_182573": 0,
    "sgoyt_count_186058": 0,
    "sgoyt_count_186592": 0,
    "sgoyt_count_190679": 0,
    "sgoyt_count_191963": 0,
    "sgoyt_count_193005": 0,
    "sgoyt_count_194479": 0,
    "sgoyt_count_194940": 0,
    "sgoyt_count_197513": 0,
    "sgoyt_count_223793": 0,
    "sgoyt_count_227011": 0,
    "sgoyt_count_228234": 0,
    "sgoyt_count_229124": 0,
    "sgoyt_count_233358": 0,
    "sgoyt_count_240624": 0,
    "sgoyt_count_241528": 0,
    "sgoyt_count_241745": 0,
    "sgoyt_count_244471": 0,
    "sgoyt_count_245355": 0,
    "sgoyt_count_246401": 0,
    "sgoyt_count_247302": 0,
    "sgoyt_count_251880": 0,
    "sgoyt_count_253515": 0,
    "sgoyt_count_255931": 0,
    "sgoyt_count_256394": 0,
    "sgoyt_count_260880": 0,
    "sgoyt_count_262008": 0,
    "sgoyt_count_262633": 0,
    "sgoyt_count_268583": 0,
    "sgoyt_count_270349": 0,
    "sgoyt_count_272126": 0,
    "sgoyt_count_276177": 0,
    "sgoyt_count_279491": 0,
    "sgoyt_count_282453": 0,
    "sgoyt_count": 94,
    "thumbnail": "https://cf.geekdo-images.com/MsBTLoQd2veQHRzQvqOTzA__thumb/img/ZYxmQMoRg-36hPsId3vaoZBL6FQ=/fit-in/200x150/filters:strip_icc()/pic2783319.jpg",
    "year_published": "2015",
    "designers": [
        "Aaron Lauster"
    ],
    "weight": 1.97,
    "rating": 6.89,
    "play_time": "15 - 30",
    "best": "9",
    "recommended": "0",
    "not_recommended": "0",
    "categories": [
        "Card Game",
        "Wargame",
        "World War II"
    ],
    "mechanics": [
        "Deck, Bag, and Pool Building",
        "Solo / Solitaire Game"
    ],
    "expansions": [
        {
            "expansion_id": "238213",
            "expansion_name": "Airborne Commander: SNAFU",
            "expansion_bgg_link": "https://boardgamegeek.com/boardgame/238213"
        }
    ],
    "expansion_for": [],
    "designers_string": "Aaron Lauster",
    "categories_string": "Card Game; Wargame; World War II",
    "mechanics_string": "Deck, Bag, and Pool Building; Solo / Solitaire Game",
    "expansions_string": "{'expansion_id': '238213', 'expansion_name': 'Airborne Commander: SNAFU', 'expansion_bgg_link': 'https://boardgamegeek.com/boardgame/238213'}",
    "expansions_for_string": ""
}