{
    "game_id": "177080",
    "game_name": "Lord of the Dead",
    "bgg_link": "https://boardgamegeek.com/boardgame/177080",
    "sgoyt_entries": [
        {
            "geeklist_id": "193005",
            "geeklist_item_id": "4020278",
            "year_month": "2015/07",
            "year": "2015",
            "month": "07",
            "geeklist_item_link": "https://boardgamegeek.com/geeklist/193005/item/4020278#item4020278",
            "geeklist_host": "joestin",
            "contributor": "VincentDarlage"
        },
        {
            "geeklist_id": "194479",
            "geeklist_item_id": "4043376",
            "year_month": "2015/08",
            "year": "2015",
            "month": "08",
            "geeklist_item_link": "https://boardgamegeek.com/geeklist/194479/item/4043376#item4043376",
            "geeklist_host": "Iz Nibz",
            "contributor": "VincentDarlage"
        },
        {
            "geeklist_id": "194940",
            "geeklist_item_id": "4115441",
            "year_month": "2015/09",
            "year": "2015",
            "month": "09",
            "geeklist_item_link": "https://boardgamegeek.com/geeklist/194940/item/4115441#item4115441",
            "geeklist_host": "lukather",
            "contributor": "VincentDarlage"
        },
        {
            "geeklist_id": "197513",
            "geeklist_item_id": "4184519",
            "year_month": "2015/10",
            "year": "2015",
            "month": "10",
            "geeklist_item_link": "https://boardgamegeek.com/geeklist/197513/item/4184519#item4184519",
            "geeklist_host": "SBGrad",
            "contributor": "Redheaded Pharmacist"
        },
        {
            "geeklist_id": "197513",
            "geeklist_item_id": "4206389",
            "year_month": "2015/10",
            "year": "2015",
            "month": "10",
            "geeklist_item_link": "https://boardgamegeek.com/geeklist/197513/item/4206389#item4206389",
            "geeklist_host": "SBGrad",
            "contributor": "LegioXIX"
        },
        {
            "geeklist_id": "197513",
            "geeklist_item_id": "4208598",
            "year_month": "2015/10",
            "year": "2015",
            "month": "10",
            "geeklist_item_link": "https://boardgamegeek.com/geeklist/197513/item/4208598#item4208598",
            "geeklist_host": "SBGrad",
            "contributor": "VincentDarlage"
        }
    ],
    "sgoyt_count": 6,
    "thumbnail": "https://cf.geekdo-images.com/5rpbLEufImwLpBTM6kkzTw__thumb/img/cYQ7wYtqKAzlg2vQp8e9UXTWdM8=/fit-in/200x150/filters:strip_icc()/pic3843941.jpg",
    "year_published": "2015",
    "designers": [
        "C. S. Ferguson"
    ],
    "weight": 1.50,
    "rating": 5.67,
    "play_time": "10 - 30",
    "best": "0",
    "recommended": "0",
    "not_recommended": "0",
    "categories": [
        "Fantasy",
        "Horror",
        "Wargame"
    ],
    "mechanics": [
        "Hexagon Grid"
    ],
    "expansions": [],
    "expansion_for": [],
    "designers_string": "C. S. Ferguson",
    "categories_string": "Fantasy; Horror; Wargame",
    "mechanics_string": "Hexagon Grid",
    "expansions_string": "",
    "expansions_for_string": ""
}