{
    "game_id": "258244",
    "game_name": "Discover: Lands Unknown",
    "bgg_link": "https://boardgamegeek.com/boardgame/258244",
    "sgoyt_entries": [
        {
            "geeklist_id": "244471",
            "geeklist_item_id": "6585128",
            "year_month": "2018/12",
            "year": "2018",
            "month": "12",
            "geeklist_item_link": "https://boardgamegeek.com/geeklist/244471/item/6585128#item6585128",
            "geeklist_host": "squarepegsys",
            "contributor": "mrmagpieman"
        },
        {
            "geeklist_id": "246401",
            "geeklist_item_id": "6499571",
            "year_month": "2018/10",
            "year": "2018",
            "month": "10",
            "geeklist_item_link": "https://boardgamegeek.com/geeklist/246401/item/6499571#item6499571",
            "geeklist_host": "kevinruns262",
            "contributor": "freudianslip27"
        },
        {
            "geeklist_id": "246401",
            "geeklist_item_id": "6504058",
            "year_month": "2018/10",
            "year": "2018",
            "month": "10",
            "geeklist_item_link": "https://boardgamegeek.com/geeklist/246401/item/6504058#item6504058",
            "geeklist_host": "kevinruns262",
            "contributor": "freudianslip27"
        },
        {
            "geeklist_id": "247302",
            "geeklist_item_id": "6511973",
            "year_month": "2018/11",
            "year": "2018",
            "month": "11",
            "geeklist_item_link": "https://boardgamegeek.com/geeklist/247302/item/6511973#item6511973",
            "geeklist_host": "Albia",
            "contributor": "mournful"
        },
        {
            "geeklist_id": "247302",
            "geeklist_item_id": "6513383",
            "year_month": "2018/11",
            "year": "2018",
            "month": "11",
            "geeklist_item_link": "https://boardgamegeek.com/geeklist/247302/item/6513383#item6513383",
            "geeklist_host": "Albia",
            "contributor": "mournful"
        },
        {
            "geeklist_id": "247302",
            "geeklist_item_id": "6513451",
            "year_month": "2018/11",
            "year": "2018",
            "month": "11",
            "geeklist_item_link": "https://boardgamegeek.com/geeklist/247302/item/6513451#item6513451",
            "geeklist_host": "Albia",
            "contributor": "mournful"
        },
        {
            "geeklist_id": "247302",
            "geeklist_item_id": "6514917",
            "year_month": "2018/11",
            "year": "2018",
            "month": "11",
            "geeklist_item_link": "https://boardgamegeek.com/geeklist/247302/item/6514917#item6514917",
            "geeklist_host": "Albia",
            "contributor": "mournful"
        },
        {
            "geeklist_id": "247302",
            "geeklist_item_id": "6517843",
            "year_month": "2018/11",
            "year": "2018",
            "month": "11",
            "geeklist_item_link": "https://boardgamegeek.com/geeklist/247302/item/6517843#item6517843",
            "geeklist_host": "Albia",
            "contributor": "fractaloon"
        },
        {
            "geeklist_id": "247302",
            "geeklist_item_id": "6518207",
            "year_month": "2018/11",
            "year": "2018",
            "month": "11",
            "geeklist_item_link": "https://boardgamegeek.com/geeklist/247302/item/6518207#item6518207",
            "geeklist_host": "Albia",
            "contributor": "mournful"
        },
        {
            "geeklist_id": "247302",
            "geeklist_item_id": "6520658",
            "year_month": "2018/11",
            "year": "2018",
            "month": "11",
            "geeklist_item_link": "https://boardgamegeek.com/geeklist/247302/item/6520658#item6520658",
            "geeklist_host": "Albia",
            "contributor": "Phantom Load"
        },
        {
            "geeklist_id": "247302",
            "geeklist_item_id": "6522328",
            "year_month": "2018/11",
            "year": "2018",
            "month": "11",
            "geeklist_item_link": "https://boardgamegeek.com/geeklist/247302/item/6522328#item6522328",
            "geeklist_host": "Albia",
            "contributor": "mournful"
        },
        {
            "geeklist_id": "247302",
            "geeklist_item_id": "6529681",
            "year_month": "2018/11",
            "year": "2018",
            "month": "11",
            "geeklist_item_link": "https://boardgamegeek.com/geeklist/247302/item/6529681#item6529681",
            "geeklist_host": "Albia",
            "contributor": "mournful"
        },
        {
            "geeklist_id": "247302",
            "geeklist_item_id": "6531892",
            "year_month": "2018/11",
            "year": "2018",
            "month": "11",
            "geeklist_item_link": "https://boardgamegeek.com/geeklist/247302/item/6531892#item6531892",
            "geeklist_host": "Albia",
            "contributor": "mournful"
        },
        {
            "geeklist_id": "247302",
            "geeklist_item_id": "6532987",
            "year_month": "2018/11",
            "year": "2018",
            "month": "11",
            "geeklist_item_link": "https://boardgamegeek.com/geeklist/247302/item/6532987#item6532987",
            "geeklist_host": "Albia",
            "contributor": "mournful"
        },
        {
            "geeklist_id": "247302",
            "geeklist_item_id": "6533154",
            "year_month": "2018/11",
            "year": "2018",
            "month": "11",
            "geeklist_item_link": "https://boardgamegeek.com/geeklist/247302/item/6533154#item6533154",
            "geeklist_host": "Albia",
            "contributor": "mournful"
        },
        {
            "geeklist_id": "247302",
            "geeklist_item_id": "6568766",
            "year_month": "2018/11",
            "year": "2018",
            "month": "11",
            "geeklist_item_link": "https://boardgamegeek.com/geeklist/247302/item/6568766#item6568766",
            "geeklist_host": "Albia",
            "contributor": "sarebear62"
        },
        {
            "geeklist_id": "249922",
            "geeklist_item_id": "6635756",
            "year_month": "2019/01",
            "year": "2019",
            "month": "01",
            "geeklist_item_link": "https://boardgamegeek.com/geeklist/249922/item/6635756#item6635756",
            "geeklist_host": "runaway_meeple",
            "contributor": "LaborLawLarry"
        },
        {
            "geeklist_id": "252324",
            "geeklist_item_id": "6749903",
            "year_month": "2019/02",
            "year": "2019",
            "month": "02",
            "geeklist_item_link": "https://boardgamegeek.com/geeklist/252324/item/6749903#item6749903",
            "geeklist_host": "The_Omnius",
            "contributor": "arabuck"
        },
        {
            "geeklist_id": "255931",
            "geeklist_item_id": "6910027",
            "year_month": "2019/05",
            "year": "2019",
            "month": "05",
            "geeklist_item_link": "https://boardgamegeek.com/geeklist/255931/item/6910027#item6910027",
            "geeklist_host": "Woelf",
            "contributor": "Kyuss"
        },
        {
            "geeklist_id": "258026",
            "geeklist_item_id": "7111593",
            "year_month": "2019/08",
            "year": "2019",
            "month": "08",
            "geeklist_item_link": "https://boardgamegeek.com/geeklist/258026/item/7111593#item7111593",
            "geeklist_host": "Venom Snake",
            "contributor": "BrokenAxe"
        },
        {
            "geeklist_id": "260880",
            "geeklist_item_id": "7188923",
            "year_month": "2019/09",
            "year": "2019",
            "month": "09",
            "geeklist_item_link": "https://boardgamegeek.com/geeklist/260880/item/7188923#item7188923",
            "geeklist_host": "jgatkinsn",
            "contributor": "Ben_Bos"
        },
        {
            "geeklist_id": "275246",
            "geeklist_item_id": "7796887",
            "year_month": "2020/08",
            "year": "2020",
            "month": "08",
            "geeklist_item_link": "https://boardgamegeek.com/geeklist/275246/item/7796887#item7796887",
            "geeklist_host": "mithoron",
            "contributor": "DrHenryArmitage"
        }
    ],
    "sgoyt_count": 22,
    "thumbnail": "https://cf.geekdo-images.com/VqU_iPFSE04TL5Dytgh6GQ__thumb/img/YHdVUbgwrS9TFWVg1aXKdKW_CVE=/fit-in/200x150/filters:strip_icc()/pic4275250.jpg",
    "year_published": "2018",
    "designers": [
        "Corey Konieczka"
    ],
    "weight": 2.32,
    "rating": 5.93,
    "play_time": "60 - 120",
    "best": "16",
    "recommended": "11",
    "not_recommended": "10",
    "categories": [
        "Adventure",
        "Exploration"
    ],
    "mechanics": [
        "Modular Board",
        "Player Elimination",
        "Variable Player Powers"
    ],
    "expansions": [],
    "expansion_for": [],
    "designers_string": "Corey Konieczka",
    "categories_string": "Adventure; Exploration",
    "mechanics_string": "Modular Board; Player Elimination; Variable Player Powers",
    "expansions_string": "",
    "expansions_for_string": ""
}