{
    "game_id": "266192",
    "game_name": "Wingspan",
    "bgg_link": "https://boardgamegeek.com/boardgame/266192",
    "sgoyt_entries": [
        {
            "geeklist_id": "249922",
            "geeklist_item_id": "6622840",
            "year_month": "2019/01",
            "year": "2019",
            "month": "01",
            "geeklist_item_link": "https://boardgamegeek.com/geeklist/249922/item/6622840#item6622840",
            "geeklist_host": "runaway_meeple",
            "contributor": "Zelofheda"
        },
        {
            "geeklist_id": "249922",
            "geeklist_item_id": "6632362",
            "year_month": "2019/01",
            "year": "2019",
            "month": "01",
            "geeklist_item_link": "https://boardgamegeek.com/geeklist/249922/item/6632362#item6632362",
            "geeklist_host": "runaway_meeple",
            "contributor": "permagoof"
        },
        {
            "geeklist_id": "249922",
            "geeklist_item_id": "6638493",
            "year_month": "2019/01",
            "year": "2019",
            "month": "01",
            "geeklist_item_link": "https://boardgamegeek.com/geeklist/249922/item/6638493#item6638493",
            "geeklist_host": "runaway_meeple",
            "contributor": "Norfolk"
        },
        {
            "geeklist_id": "249922",
            "geeklist_item_id": "6641267",
            "year_month": "2019/01",
            "year": "2019",
            "month": "01",
            "geeklist_item_link": "https://boardgamegeek.com/geeklist/249922/item/6641267#item6641267",
            "geeklist_host": "runaway_meeple",
            "contributor": "TacoKnight"
        },
        {
            "geeklist_id": "249922",
            "geeklist_item_id": "6649575",
            "year_month": "2019/01",
            "year": "2019",
            "month": "01",
            "geeklist_item_link": "https://boardgamegeek.com/geeklist/249922/item/6649575#item6649575",
            "geeklist_host": "runaway_meeple",
            "contributor": "BSLBobby"
        },
        {
            "geeklist_id": "249922",
            "geeklist_item_id": "6656807",
            "year_month": "2019/01",
            "year": "2019",
            "month": "01",
            "geeklist_item_link": "https://boardgamegeek.com/geeklist/249922/item/6656807#item6656807",
            "geeklist_host": "runaway_meeple",
            "contributor": "SgtTenor"
        },
        {
            "geeklist_id": "249922",
            "geeklist_item_id": "6657104",
            "year_month": "2019/01",
            "year": "2019",
            "month": "01",
            "geeklist_item_link": "https://boardgamegeek.com/geeklist/249922/item/6657104#item6657104",
            "geeklist_host": "runaway_meeple",
            "contributor": "BSLBobby"
        },
        {
            "geeklist_id": "249922",
            "geeklist_item_id": "6659002",
            "year_month": "2019/01",
            "year": "2019",
            "month": "01",
            "geeklist_item_link": "https://boardgamegeek.com/geeklist/249922/item/6659002#item6659002",
            "geeklist_host": "runaway_meeple",
            "contributor": "DFu4ever"
        },
        {
            "geeklist_id": "249922",
            "geeklist_item_id": "6659587",
            "year_month": "2019/01",
            "year": "2019",
            "month": "01",
            "geeklist_item_link": "https://boardgamegeek.com/geeklist/249922/item/6659587#item6659587",
            "geeklist_host": "runaway_meeple",
            "contributor": "DocSavage2001"
        },
        {
            "geeklist_id": "249922",
            "geeklist_item_id": "6661524",
            "year_month": "2019/01",
            "year": "2019",
            "month": "01",
            "geeklist_item_link": "https://boardgamegeek.com/geeklist/249922/item/6661524#item6661524",
            "geeklist_host": "runaway_meeple",
            "contributor": "bills933"
        },
        {
            "geeklist_id": "249922",
            "geeklist_item_id": "6661905",
            "year_month": "2019/01",
            "year": "2019",
            "month": "01",
            "geeklist_item_link": "https://boardgamegeek.com/geeklist/249922/item/6661905#item6661905",
            "geeklist_host": "runaway_meeple",
            "contributor": "mogust"
        },
        {
            "geeklist_id": "249922",
            "geeklist_item_id": "6665241",
            "year_month": "2019/01",
            "year": "2019",
            "month": "01",
            "geeklist_item_link": "https://boardgamegeek.com/geeklist/249922/item/6665241#item6665241",
            "geeklist_host": "runaway_meeple",
            "contributor": "Xabbusan"
        },
        {
            "geeklist_id": "249922",
            "geeklist_item_id": "6665425",
            "year_month": "2019/01",
            "year": "2019",
            "month": "01",
            "geeklist_item_link": "https://boardgamegeek.com/geeklist/249922/item/6665425#item6665425",
            "geeklist_host": "runaway_meeple",
            "contributor": "Langalore"
        },
        {
            "geeklist_id": "249922",
            "geeklist_item_id": "6665595",
            "year_month": "2019/01",
            "year": "2019",
            "month": "01",
            "geeklist_item_link": "https://boardgamegeek.com/geeklist/249922/item/6665595#item6665595",
            "geeklist_host": "runaway_meeple",
            "contributor": "mogust"
        },
        {
            "geeklist_id": "249922",
            "geeklist_item_id": "6669084",
            "year_month": "2019/01",
            "year": "2019",
            "month": "01",
            "geeklist_item_link": "https://boardgamegeek.com/geeklist/249922/item/6669084#item6669084",
            "geeklist_host": "runaway_meeple",
            "contributor": "mogust"
        },
        {
            "geeklist_id": "249922",
            "geeklist_item_id": "6669092",
            "year_month": "2019/01",
            "year": "2019",
            "month": "01",
            "geeklist_item_link": "https://boardgamegeek.com/geeklist/249922/item/6669092#item6669092",
            "geeklist_host": "runaway_meeple",
            "contributor": "BSLBobby"
        },
        {
            "geeklist_id": "249922",
            "geeklist_item_id": "6671667",
            "year_month": "2019/01",
            "year": "2019",
            "month": "01",
            "geeklist_item_link": "https://boardgamegeek.com/geeklist/249922/item/6671667#item6671667",
            "geeklist_host": "runaway_meeple",
            "contributor": "avocategory"
        },
        {
            "geeklist_id": "249922",
            "geeklist_item_id": "6679736",
            "year_month": "2019/01",
            "year": "2019",
            "month": "01",
            "geeklist_item_link": "https://boardgamegeek.com/geeklist/249922/item/6679736#item6679736",
            "geeklist_host": "runaway_meeple",
            "contributor": "Xabbusan"
        },
        {
            "geeklist_id": "249922",
            "geeklist_item_id": "6682351",
            "year_month": "2019/01",
            "year": "2019",
            "month": "01",
            "geeklist_item_link": "https://boardgamegeek.com/geeklist/249922/item/6682351#item6682351",
            "geeklist_host": "runaway_meeple",
            "contributor": "overhaul"
        },
        {
            "geeklist_id": "249922",
            "geeklist_item_id": "6683554",
            "year_month": "2019/01",
            "year": "2019",
            "month": "01",
            "geeklist_item_link": "https://boardgamegeek.com/geeklist/249922/item/6683554#item6683554",
            "geeklist_host": "runaway_meeple",
            "contributor": "mogust"
        },
        {
            "geeklist_id": "249922",
            "geeklist_item_id": "6686395",
            "year_month": "2019/01",
            "year": "2019",
            "month": "01",
            "geeklist_item_link": "https://boardgamegeek.com/geeklist/249922/item/6686395#item6686395",
            "geeklist_host": "runaway_meeple",
            "contributor": "bills933"
        },
        {
            "geeklist_id": "249922",
            "geeklist_item_id": "6687711",
            "year_month": "2019/01",
            "year": "2019",
            "month": "01",
            "geeklist_item_link": "https://boardgamegeek.com/geeklist/249922/item/6687711#item6687711",
            "geeklist_host": "runaway_meeple",
            "contributor": "mogust"
        },
        {
            "geeklist_id": "251846",
            "geeklist_item_id": "6778939",
            "year_month": "2019/03",
            "year": "2019",
            "month": "03",
            "geeklist_item_link": "https://boardgamegeek.com/geeklist/251846/item/6778939#item6778939",
            "geeklist_host": "Donutz McGoo",
            "contributor": "permagoof"
        },
        {
            "geeklist_id": "251846",
            "geeklist_item_id": "6780674",
            "year_month": "2019/03",
            "year": "2019",
            "month": "03",
            "geeklist_item_link": "https://boardgamegeek.com/geeklist/251846/item/6780674#item6780674",
            "geeklist_host": "Donutz McGoo",
            "contributor": "mogust"
        },
        {
            "geeklist_id": "251846",
            "geeklist_item_id": "6785327",
            "year_month": "2019/03",
            "year": "2019",
            "month": "03",
            "geeklist_item_link": "https://boardgamegeek.com/geeklist/251846/item/6785327#item6785327",
            "geeklist_host": "Donutz McGoo",
            "contributor": "DocSavage2001"
        },
        {
            "geeklist_id": "251846",
            "geeklist_item_id": "6794696",
            "year_month": "2019/03",
            "year": "2019",
            "month": "03",
            "geeklist_item_link": "https://boardgamegeek.com/geeklist/251846/item/6794696#item6794696",
            "geeklist_host": "Donutz McGoo",
            "contributor": "Kush7"
        },
        {
            "geeklist_id": "251846",
            "geeklist_item_id": "6796095",
            "year_month": "2019/03",
            "year": "2019",
            "month": "03",
            "geeklist_item_link": "https://boardgamegeek.com/geeklist/251846/item/6796095#item6796095",
            "geeklist_host": "Donutz McGoo",
            "contributor": "mrmagpieman"
        },
        {
            "geeklist_id": "251846",
            "geeklist_item_id": "6796158",
            "year_month": "2019/03",
            "year": "2019",
            "month": "03",
            "geeklist_item_link": "https://boardgamegeek.com/geeklist/251846/item/6796158#item6796158",
            "geeklist_host": "Donutz McGoo",
            "contributor": "Albia"
        },
        {
            "geeklist_id": "251846",
            "geeklist_item_id": "6800099",
            "year_month": "2019/03",
            "year": "2019",
            "month": "03",
            "geeklist_item_link": "https://boardgamegeek.com/geeklist/251846/item/6800099#item6800099",
            "geeklist_host": "Donutz McGoo",
            "contributor": "mrmagpieman"
        },
        {
            "geeklist_id": "251846",
            "geeklist_item_id": "6804107",
            "year_month": "2019/03",
            "year": "2019",
            "month": "03",
            "geeklist_item_link": "https://boardgamegeek.com/geeklist/251846/item/6804107#item6804107",
            "geeklist_host": "Donutz McGoo",
            "contributor": "cirdan"
        },
        {
            "geeklist_id": "251846",
            "geeklist_item_id": "6804734",
            "year_month": "2019/03",
            "year": "2019",
            "month": "03",
            "geeklist_item_link": "https://boardgamegeek.com/geeklist/251846/item/6804734#item6804734",
            "geeklist_host": "Donutz McGoo",
            "contributor": "Kush7"
        },
        {
            "geeklist_id": "251846",
            "geeklist_item_id": "6806745",
            "year_month": "2019/03",
            "year": "2019",
            "month": "03",
            "geeklist_item_link": "https://boardgamegeek.com/geeklist/251846/item/6806745#item6806745",
            "geeklist_host": "Donutz McGoo",
            "contributor": "Get Earthworm"
        },
        {
            "geeklist_id": "251846",
            "geeklist_item_id": "6807747",
            "year_month": "2019/03",
            "year": "2019",
            "month": "03",
            "geeklist_item_link": "https://boardgamegeek.com/geeklist/251846/item/6807747#item6807747",
            "geeklist_host": "Donutz McGoo",
            "contributor": "mogust"
        },
        {
            "geeklist_id": "251846",
            "geeklist_item_id": "6813152",
            "year_month": "2019/03",
            "year": "2019",
            "month": "03",
            "geeklist_item_link": "https://boardgamegeek.com/geeklist/251846/item/6813152#item6813152",
            "geeklist_host": "Donutz McGoo",
            "contributor": "Albia"
        },
        {
            "geeklist_id": "251846",
            "geeklist_item_id": "6816287",
            "year_month": "2019/03",
            "year": "2019",
            "month": "03",
            "geeklist_item_link": "https://boardgamegeek.com/geeklist/251846/item/6816287#item6816287",
            "geeklist_host": "Donutz McGoo",
            "contributor": "mrmagpieman"
        },
        {
            "geeklist_id": "251846",
            "geeklist_item_id": "6827671",
            "year_month": "2019/03",
            "year": "2019",
            "month": "03",
            "geeklist_item_link": "https://boardgamegeek.com/geeklist/251846/item/6827671#item6827671",
            "geeklist_host": "Donutz McGoo",
            "contributor": "Daemonsson"
        },
        {
            "geeklist_id": "251880",
            "geeklist_item_id": "6831328",
            "year_month": "2019/04",
            "year": "2019",
            "month": "04",
            "geeklist_item_link": "https://boardgamegeek.com/geeklist/251880/item/6831328#item6831328",
            "geeklist_host": "garyrbrooks",
            "contributor": "mogust"
        },
        {
            "geeklist_id": "251880",
            "geeklist_item_id": "6833305",
            "year_month": "2019/04",
            "year": "2019",
            "month": "04",
            "geeklist_item_link": "https://boardgamegeek.com/geeklist/251880/item/6833305#item6833305",
            "geeklist_host": "garyrbrooks",
            "contributor": "BrokenAxe"
        },
        {
            "geeklist_id": "251880",
            "geeklist_item_id": "6834393",
            "year_month": "2019/04",
            "year": "2019",
            "month": "04",
            "geeklist_item_link": "https://boardgamegeek.com/geeklist/251880/item/6834393#item6834393",
            "geeklist_host": "garyrbrooks",
            "contributor": "DocSavage2001"
        },
        {
            "geeklist_id": "251880",
            "geeklist_item_id": "6837000",
            "year_month": "2019/04",
            "year": "2019",
            "month": "04",
            "geeklist_item_link": "https://boardgamegeek.com/geeklist/251880/item/6837000#item6837000",
            "geeklist_host": "garyrbrooks",
            "contributor": "BrokenAxe"
        },
        {
            "geeklist_id": "251880",
            "geeklist_item_id": "6837080",
            "year_month": "2019/04",
            "year": "2019",
            "month": "04",
            "geeklist_item_link": "https://boardgamegeek.com/geeklist/251880/item/6837080#item6837080",
            "geeklist_host": "garyrbrooks",
            "contributor": "labrhat22"
        },
        {
            "geeklist_id": "251880",
            "geeklist_item_id": "6839441",
            "year_month": "2019/04",
            "year": "2019",
            "month": "04",
            "geeklist_item_link": "https://boardgamegeek.com/geeklist/251880/item/6839441#item6839441",
            "geeklist_host": "garyrbrooks",
            "contributor": "mrmagpieman"
        },
        {
            "geeklist_id": "251880",
            "geeklist_item_id": "6840515",
            "year_month": "2019/04",
            "year": "2019",
            "month": "04",
            "geeklist_item_link": "https://boardgamegeek.com/geeklist/251880/item/6840515#item6840515",
            "geeklist_host": "garyrbrooks",
            "contributor": "sarebear62"
        },
        {
            "geeklist_id": "251880",
            "geeklist_item_id": "6842556",
            "year_month": "2019/04",
            "year": "2019",
            "month": "04",
            "geeklist_item_link": "https://boardgamegeek.com/geeklist/251880/item/6842556#item6842556",
            "geeklist_host": "garyrbrooks",
            "contributor": "Kush7"
        },
        {
            "geeklist_id": "251880",
            "geeklist_item_id": "6843310",
            "year_month": "2019/04",
            "year": "2019",
            "month": "04",
            "geeklist_item_link": "https://boardgamegeek.com/geeklist/251880/item/6843310#item6843310",
            "geeklist_host": "garyrbrooks",
            "contributor": "Kush7"
        },
        {
            "geeklist_id": "251880",
            "geeklist_item_id": "6845085",
            "year_month": "2019/04",
            "year": "2019",
            "month": "04",
            "geeklist_item_link": "https://boardgamegeek.com/geeklist/251880/item/6845085#item6845085",
            "geeklist_host": "garyrbrooks",
            "contributor": "mogust"
        },
        {
            "geeklist_id": "251880",
            "geeklist_item_id": "6864197",
            "year_month": "2019/04",
            "year": "2019",
            "month": "04",
            "geeklist_item_link": "https://boardgamegeek.com/geeklist/251880/item/6864197#item6864197",
            "geeklist_host": "garyrbrooks",
            "contributor": "MadMihi"
        },
        {
            "geeklist_id": "251880",
            "geeklist_item_id": "6866677",
            "year_month": "2019/04",
            "year": "2019",
            "month": "04",
            "geeklist_item_link": "https://boardgamegeek.com/geeklist/251880/item/6866677#item6866677",
            "geeklist_host": "garyrbrooks",
            "contributor": "MadMihi"
        },
        {
            "geeklist_id": "251880",
            "geeklist_item_id": "6866888",
            "year_month": "2019/04",
            "year": "2019",
            "month": "04",
            "geeklist_item_link": "https://boardgamegeek.com/geeklist/251880/item/6866888#item6866888",
            "geeklist_host": "garyrbrooks",
            "contributor": "neotrunks2002"
        },
        {
            "geeklist_id": "251880",
            "geeklist_item_id": "6868525",
            "year_month": "2019/04",
            "year": "2019",
            "month": "04",
            "geeklist_item_link": "https://boardgamegeek.com/geeklist/251880/item/6868525#item6868525",
            "geeklist_host": "garyrbrooks",
            "contributor": "neotrunks2002"
        },
        {
            "geeklist_id": "251880",
            "geeklist_item_id": "6873162",
            "year_month": "2019/04",
            "year": "2019",
            "month": "04",
            "geeklist_item_link": "https://boardgamegeek.com/geeklist/251880/item/6873162#item6873162",
            "geeklist_host": "garyrbrooks",
            "contributor": "Xabbusan"
        },
        {
            "geeklist_id": "251880",
            "geeklist_item_id": "6873493",
            "year_month": "2019/04",
            "year": "2019",
            "month": "04",
            "geeklist_item_link": "https://boardgamegeek.com/geeklist/251880/item/6873493#item6873493",
            "geeklist_host": "garyrbrooks",
            "contributor": "eastwoodk"
        },
        {
            "geeklist_id": "251880",
            "geeklist_item_id": "6884776",
            "year_month": "2019/04",
            "year": "2019",
            "month": "04",
            "geeklist_item_link": "https://boardgamegeek.com/geeklist/251880/item/6884776#item6884776",
            "geeklist_host": "garyrbrooks",
            "contributor": "eastwoodk"
        },
        {
            "geeklist_id": "251880",
            "geeklist_item_id": "6886548",
            "year_month": "2019/04",
            "year": "2019",
            "month": "04",
            "geeklist_item_link": "https://boardgamegeek.com/geeklist/251880/item/6886548#item6886548",
            "geeklist_host": "garyrbrooks",
            "contributor": "eastwoodk"
        },
        {
            "geeklist_id": "251880",
            "geeklist_item_id": "6889787",
            "year_month": "2019/04",
            "year": "2019",
            "month": "04",
            "geeklist_item_link": "https://boardgamegeek.com/geeklist/251880/item/6889787#item6889787",
            "geeklist_host": "garyrbrooks",
            "contributor": "Albia"
        },
        {
            "geeklist_id": "252324",
            "geeklist_item_id": "6698511",
            "year_month": "2019/02",
            "year": "2019",
            "month": "02",
            "geeklist_item_link": "https://boardgamegeek.com/geeklist/252324/item/6698511#item6698511",
            "geeklist_host": "The_Omnius",
            "contributor": "Kanstandler"
        },
        {
            "geeklist_id": "252324",
            "geeklist_item_id": "6700600",
            "year_month": "2019/02",
            "year": "2019",
            "month": "02",
            "geeklist_item_link": "https://boardgamegeek.com/geeklist/252324/item/6700600#item6700600",
            "geeklist_host": "The_Omnius",
            "contributor": "mogust"
        },
        {
            "geeklist_id": "252324",
            "geeklist_item_id": "6704369",
            "year_month": "2019/02",
            "year": "2019",
            "month": "02",
            "geeklist_item_link": "https://boardgamegeek.com/geeklist/252324/item/6704369#item6704369",
            "geeklist_host": "The_Omnius",
            "contributor": "DocSavage2001"
        },
        {
            "geeklist_id": "252324",
            "geeklist_item_id": "6710316",
            "year_month": "2019/02",
            "year": "2019",
            "month": "02",
            "geeklist_item_link": "https://boardgamegeek.com/geeklist/252324/item/6710316#item6710316",
            "geeklist_host": "The_Omnius",
            "contributor": "permagoof"
        },
        {
            "geeklist_id": "252324",
            "geeklist_item_id": "6711402",
            "year_month": "2019/02",
            "year": "2019",
            "month": "02",
            "geeklist_item_link": "https://boardgamegeek.com/geeklist/252324/item/6711402#item6711402",
            "geeklist_host": "The_Omnius",
            "contributor": "mogust"
        },
        {
            "geeklist_id": "252324",
            "geeklist_item_id": "6754214",
            "year_month": "2019/02",
            "year": "2019",
            "month": "02",
            "geeklist_item_link": "https://boardgamegeek.com/geeklist/252324/item/6754214#item6754214",
            "geeklist_host": "The_Omnius",
            "contributor": "Olvenskol"
        },
        {
            "geeklist_id": "252324",
            "geeklist_item_id": "6760463",
            "year_month": "2019/02",
            "year": "2019",
            "month": "02",
            "geeklist_item_link": "https://boardgamegeek.com/geeklist/252324/item/6760463#item6760463",
            "geeklist_host": "The_Omnius",
            "contributor": "labrhat22"
        },
        {
            "geeklist_id": "252324",
            "geeklist_item_id": "6761245",
            "year_month": "2019/02",
            "year": "2019",
            "month": "02",
            "geeklist_item_link": "https://boardgamegeek.com/geeklist/252324/item/6761245#item6761245",
            "geeklist_host": "The_Omnius",
            "contributor": "metajack"
        },
        {
            "geeklist_id": "252324",
            "geeklist_item_id": "6767479",
            "year_month": "2019/02",
            "year": "2019",
            "month": "02",
            "geeklist_item_link": "https://boardgamegeek.com/geeklist/252324/item/6767479#item6767479",
            "geeklist_host": "The_Omnius",
            "contributor": "overhaul"
        },
        {
            "geeklist_id": "253515",
            "geeklist_item_id": "7017081",
            "year_month": "2019/07",
            "year": "2019",
            "month": "07",
            "geeklist_item_link": "https://boardgamegeek.com/geeklist/253515/item/7017081#item7017081",
            "geeklist_host": "labrhat22",
            "contributor": "DocSavage2001"
        },
        {
            "geeklist_id": "253515",
            "geeklist_item_id": "7017691",
            "year_month": "2019/07",
            "year": "2019",
            "month": "07",
            "geeklist_item_link": "https://boardgamegeek.com/geeklist/253515/item/7017691#item7017691",
            "geeklist_host": "labrhat22",
            "contributor": "eastwoodk"
        },
        {
            "geeklist_id": "253515",
            "geeklist_item_id": "7023219",
            "year_month": "2019/07",
            "year": "2019",
            "month": "07",
            "geeklist_item_link": "https://boardgamegeek.com/geeklist/253515/item/7023219#item7023219",
            "geeklist_host": "labrhat22",
            "contributor": "mrmagpieman"
        },
        {
            "geeklist_id": "253515",
            "geeklist_item_id": "7023740",
            "year_month": "2019/07",
            "year": "2019",
            "month": "07",
            "geeklist_item_link": "https://boardgamegeek.com/geeklist/253515/item/7023740#item7023740",
            "geeklist_host": "labrhat22",
            "contributor": "Robble"
        },
        {
            "geeklist_id": "253515",
            "geeklist_item_id": "7026520",
            "year_month": "2019/07",
            "year": "2019",
            "month": "07",
            "geeklist_item_link": "https://boardgamegeek.com/geeklist/253515/item/7026520#item7026520",
            "geeklist_host": "labrhat22",
            "contributor": "chuft"
        },
        {
            "geeklist_id": "253515",
            "geeklist_item_id": "7029770",
            "year_month": "2019/07",
            "year": "2019",
            "month": "07",
            "geeklist_item_link": "https://boardgamegeek.com/geeklist/253515/item/7029770#item7029770",
            "geeklist_host": "labrhat22",
            "contributor": "Venom Snake"
        },
        {
            "geeklist_id": "253515",
            "geeklist_item_id": "7034439",
            "year_month": "2019/07",
            "year": "2019",
            "month": "07",
            "geeklist_item_link": "https://boardgamegeek.com/geeklist/253515/item/7034439#item7034439",
            "geeklist_host": "labrhat22",
            "contributor": "jeffrhind"
        },
        {
            "geeklist_id": "253515",
            "geeklist_item_id": "7040903",
            "year_month": "2019/07",
            "year": "2019",
            "month": "07",
            "geeklist_item_link": "https://boardgamegeek.com/geeklist/253515/item/7040903#item7040903",
            "geeklist_host": "labrhat22",
            "contributor": "Albia"
        },
        {
            "geeklist_id": "253515",
            "geeklist_item_id": "7042924",
            "year_month": "2019/07",
            "year": "2019",
            "month": "07",
            "geeklist_item_link": "https://boardgamegeek.com/geeklist/253515/item/7042924#item7042924",
            "geeklist_host": "labrhat22",
            "contributor": "jeffrhind"
        },
        {
            "geeklist_id": "253515",
            "geeklist_item_id": "7049592",
            "year_month": "2019/07",
            "year": "2019",
            "month": "07",
            "geeklist_item_link": "https://boardgamegeek.com/geeklist/253515/item/7049592#item7049592",
            "geeklist_host": "labrhat22",
            "contributor": "Venom Snake"
        },
        {
            "geeklist_id": "253515",
            "geeklist_item_id": "7053457",
            "year_month": "2019/07",
            "year": "2019",
            "month": "07",
            "geeklist_item_link": "https://boardgamegeek.com/geeklist/253515/item/7053457#item7053457",
            "geeklist_host": "labrhat22",
            "contributor": "jgatkinsn"
        },
        {
            "geeklist_id": "253515",
            "geeklist_item_id": "7054609",
            "year_month": "2019/07",
            "year": "2019",
            "month": "07",
            "geeklist_item_link": "https://boardgamegeek.com/geeklist/253515/item/7054609#item7054609",
            "geeklist_host": "labrhat22",
            "contributor": "permagoof"
        },
        {
            "geeklist_id": "255931",
            "geeklist_item_id": "6889963",
            "year_month": "2019/05",
            "year": "2019",
            "month": "05",
            "geeklist_item_link": "https://boardgamegeek.com/geeklist/255931/item/6889963#item6889963",
            "geeklist_host": "Woelf",
            "contributor": "RiderHat"
        },
        {
            "geeklist_id": "255931",
            "geeklist_item_id": "6890212",
            "year_month": "2019/05",
            "year": "2019",
            "month": "05",
            "geeklist_item_link": "https://boardgamegeek.com/geeklist/255931/item/6890212#item6890212",
            "geeklist_host": "Woelf",
            "contributor": "skyzero"
        },
        {
            "geeklist_id": "255931",
            "geeklist_item_id": "6895885",
            "year_month": "2019/05",
            "year": "2019",
            "month": "05",
            "geeklist_item_link": "https://boardgamegeek.com/geeklist/255931/item/6895885#item6895885",
            "geeklist_host": "Woelf",
            "contributor": "DocSavage2001"
        },
        {
            "geeklist_id": "255931",
            "geeklist_item_id": "6896720",
            "year_month": "2019/05",
            "year": "2019",
            "month": "05",
            "geeklist_item_link": "https://boardgamegeek.com/geeklist/255931/item/6896720#item6896720",
            "geeklist_host": "Woelf",
            "contributor": "BrokenAxe"
        },
        {
            "geeklist_id": "255931",
            "geeklist_item_id": "6902856",
            "year_month": "2019/05",
            "year": "2019",
            "month": "05",
            "geeklist_item_link": "https://boardgamegeek.com/geeklist/255931/item/6902856#item6902856",
            "geeklist_host": "Woelf",
            "contributor": "mogust"
        },
        {
            "geeklist_id": "255931",
            "geeklist_item_id": "6903909",
            "year_month": "2019/05",
            "year": "2019",
            "month": "05",
            "geeklist_item_link": "https://boardgamegeek.com/geeklist/255931/item/6903909#item6903909",
            "geeklist_host": "Woelf",
            "contributor": "mrmagpieman"
        },
        {
            "geeklist_id": "255931",
            "geeklist_item_id": "6938533",
            "year_month": "2019/05",
            "year": "2019",
            "month": "05",
            "geeklist_item_link": "https://boardgamegeek.com/geeklist/255931/item/6938533#item6938533",
            "geeklist_host": "Woelf",
            "contributor": "Haywood"
        },
        {
            "geeklist_id": "255931",
            "geeklist_item_id": "6940199",
            "year_month": "2019/05",
            "year": "2019",
            "month": "05",
            "geeklist_item_link": "https://boardgamegeek.com/geeklist/255931/item/6940199#item6940199",
            "geeklist_host": "Woelf",
            "contributor": "Haywood"
        },
        {
            "geeklist_id": "255931",
            "geeklist_item_id": "6945953",
            "year_month": "2019/05",
            "year": "2019",
            "month": "05",
            "geeklist_item_link": "https://boardgamegeek.com/geeklist/255931/item/6945953#item6945953",
            "geeklist_host": "Woelf",
            "contributor": "Xabbusan"
        },
        {
            "geeklist_id": "255931",
            "geeklist_item_id": "6956488",
            "year_month": "2019/05",
            "year": "2019",
            "month": "05",
            "geeklist_item_link": "https://boardgamegeek.com/geeklist/255931/item/6956488#item6956488",
            "geeklist_host": "Woelf",
            "contributor": "WingTale"
        },
        {
            "geeklist_id": "256394",
            "geeklist_item_id": "6962599",
            "year_month": "2019/06",
            "year": "2019",
            "month": "06",
            "geeklist_item_link": "https://boardgamegeek.com/geeklist/256394/item/6962599#item6962599",
            "geeklist_host": "magic_erwt",
            "contributor": "DocSavage2001"
        },
        {
            "geeklist_id": "256394",
            "geeklist_item_id": "6972543",
            "year_month": "2019/06",
            "year": "2019",
            "month": "06",
            "geeklist_item_link": "https://boardgamegeek.com/geeklist/256394/item/6972543#item6972543",
            "geeklist_host": "magic_erwt",
            "contributor": "Venom Snake"
        },
        {
            "geeklist_id": "256394",
            "geeklist_item_id": "6974601",
            "year_month": "2019/06",
            "year": "2019",
            "month": "06",
            "geeklist_item_link": "https://boardgamegeek.com/geeklist/256394/item/6974601#item6974601",
            "geeklist_host": "magic_erwt",
            "contributor": "Dgore1"
        },
        {
            "geeklist_id": "256394",
            "geeklist_item_id": "6981898",
            "year_month": "2019/06",
            "year": "2019",
            "month": "06",
            "geeklist_item_link": "https://boardgamegeek.com/geeklist/256394/item/6981898#item6981898",
            "geeklist_host": "magic_erwt",
            "contributor": "Marctimmins89"
        },
        {
            "geeklist_id": "256394",
            "geeklist_item_id": "6982455",
            "year_month": "2019/06",
            "year": "2019",
            "month": "06",
            "geeklist_item_link": "https://boardgamegeek.com/geeklist/256394/item/6982455#item6982455",
            "geeklist_host": "magic_erwt",
            "contributor": "Venom Snake"
        },
        {
            "geeklist_id": "256394",
            "geeklist_item_id": "6982940",
            "year_month": "2019/06",
            "year": "2019",
            "month": "06",
            "geeklist_item_link": "https://boardgamegeek.com/geeklist/256394/item/6982940#item6982940",
            "geeklist_host": "magic_erwt",
            "contributor": "ThroughTheDeckGlass"
        },
        {
            "geeklist_id": "256394",
            "geeklist_item_id": "6985528",
            "year_month": "2019/06",
            "year": "2019",
            "month": "06",
            "geeklist_item_link": "https://boardgamegeek.com/geeklist/256394/item/6985528#item6985528",
            "geeklist_host": "magic_erwt",
            "contributor": "Robble"
        },
        {
            "geeklist_id": "256394",
            "geeklist_item_id": "6989628",
            "year_month": "2019/06",
            "year": "2019",
            "month": "06",
            "geeklist_item_link": "https://boardgamegeek.com/geeklist/256394/item/6989628#item6989628",
            "geeklist_host": "magic_erwt",
            "contributor": "thredith"
        },
        {
            "geeklist_id": "256394",
            "geeklist_item_id": "6990413",
            "year_month": "2019/06",
            "year": "2019",
            "month": "06",
            "geeklist_item_link": "https://boardgamegeek.com/geeklist/256394/item/6990413#item6990413",
            "geeklist_host": "magic_erwt",
            "contributor": "cirdan"
        },
        {
            "geeklist_id": "256394",
            "geeklist_item_id": "6991911",
            "year_month": "2019/06",
            "year": "2019",
            "month": "06",
            "geeklist_item_link": "https://boardgamegeek.com/geeklist/256394/item/6991911#item6991911",
            "geeklist_host": "magic_erwt",
            "contributor": "thredith"
        },
        {
            "geeklist_id": "256394",
            "geeklist_item_id": "6992307",
            "year_month": "2019/06",
            "year": "2019",
            "month": "06",
            "geeklist_item_link": "https://boardgamegeek.com/geeklist/256394/item/6992307#item6992307",
            "geeklist_host": "magic_erwt",
            "contributor": "Marctimmins89"
        },
        {
            "geeklist_id": "256394",
            "geeklist_item_id": "6998766",
            "year_month": "2019/06",
            "year": "2019",
            "month": "06",
            "geeklist_item_link": "https://boardgamegeek.com/geeklist/256394/item/6998766#item6998766",
            "geeklist_host": "magic_erwt",
            "contributor": "jgatkinsn"
        },
        {
            "geeklist_id": "256394",
            "geeklist_item_id": "6999297",
            "year_month": "2019/06",
            "year": "2019",
            "month": "06",
            "geeklist_item_link": "https://boardgamegeek.com/geeklist/256394/item/6999297#item6999297",
            "geeklist_host": "magic_erwt",
            "contributor": "thredith"
        },
        {
            "geeklist_id": "256394",
            "geeklist_item_id": "7000929",
            "year_month": "2019/06",
            "year": "2019",
            "month": "06",
            "geeklist_item_link": "https://boardgamegeek.com/geeklist/256394/item/7000929#item7000929",
            "geeklist_host": "magic_erwt",
            "contributor": "jgatkinsn"
        },
        {
            "geeklist_id": "256394",
            "geeklist_item_id": "7010578",
            "year_month": "2019/06",
            "year": "2019",
            "month": "06",
            "geeklist_item_link": "https://boardgamegeek.com/geeklist/256394/item/7010578#item7010578",
            "geeklist_host": "magic_erwt",
            "contributor": "WingTale"
        },
        {
            "geeklist_id": "256394",
            "geeklist_item_id": "7010634",
            "year_month": "2019/06",
            "year": "2019",
            "month": "06",
            "geeklist_item_link": "https://boardgamegeek.com/geeklist/256394/item/7010634#item7010634",
            "geeklist_host": "magic_erwt",
            "contributor": "Albia"
        },
        {
            "geeklist_id": "258026",
            "geeklist_item_id": "7066059",
            "year_month": "2019/08",
            "year": "2019",
            "month": "08",
            "geeklist_item_link": "https://boardgamegeek.com/geeklist/258026/item/7066059#item7066059",
            "geeklist_host": "Venom Snake",
            "contributor": "DocSavage2001"
        },
        {
            "geeklist_id": "258026",
            "geeklist_item_id": "7076348",
            "year_month": "2019/08",
            "year": "2019",
            "month": "08",
            "geeklist_item_link": "https://boardgamegeek.com/geeklist/258026/item/7076348#item7076348",
            "geeklist_host": "Venom Snake",
            "contributor": "Haywood"
        },
        {
            "geeklist_id": "258026",
            "geeklist_item_id": "7087719",
            "year_month": "2019/08",
            "year": "2019",
            "month": "08",
            "geeklist_item_link": "https://boardgamegeek.com/geeklist/258026/item/7087719#item7087719",
            "geeklist_host": "Venom Snake",
            "contributor": "itazzy"
        },
        {
            "geeklist_id": "258026",
            "geeklist_item_id": "7089292",
            "year_month": "2019/08",
            "year": "2019",
            "month": "08",
            "geeklist_item_link": "https://boardgamegeek.com/geeklist/258026/item/7089292#item7089292",
            "geeklist_host": "Venom Snake",
            "contributor": "desertrat2020"
        },
        {
            "geeklist_id": "258026",
            "geeklist_item_id": "7089866",
            "year_month": "2019/08",
            "year": "2019",
            "month": "08",
            "geeklist_item_link": "https://boardgamegeek.com/geeklist/258026/item/7089866#item7089866",
            "geeklist_host": "Venom Snake",
            "contributor": "TheStoicEmperor"
        },
        {
            "geeklist_id": "258026",
            "geeklist_item_id": "7092141",
            "year_month": "2019/08",
            "year": "2019",
            "month": "08",
            "geeklist_item_link": "https://boardgamegeek.com/geeklist/258026/item/7092141#item7092141",
            "geeklist_host": "Venom Snake",
            "contributor": "Albia"
        },
        {
            "geeklist_id": "258026",
            "geeklist_item_id": "7093518",
            "year_month": "2019/08",
            "year": "2019",
            "month": "08",
            "geeklist_item_link": "https://boardgamegeek.com/geeklist/258026/item/7093518#item7093518",
            "geeklist_host": "Venom Snake",
            "contributor": "ParisPink"
        },
        {
            "geeklist_id": "258026",
            "geeklist_item_id": "7110022",
            "year_month": "2019/08",
            "year": "2019",
            "month": "08",
            "geeklist_item_link": "https://boardgamegeek.com/geeklist/258026/item/7110022#item7110022",
            "geeklist_host": "Venom Snake",
            "contributor": "Robble"
        },
        {
            "geeklist_id": "258026",
            "geeklist_item_id": "7114468",
            "year_month": "2019/08",
            "year": "2019",
            "month": "08",
            "geeklist_item_link": "https://boardgamegeek.com/geeklist/258026/item/7114468#item7114468",
            "geeklist_host": "Venom Snake",
            "contributor": "Annanicolesmith"
        },
        {
            "geeklist_id": "258026",
            "geeklist_item_id": "7127463",
            "year_month": "2019/08",
            "year": "2019",
            "month": "08",
            "geeklist_item_link": "https://boardgamegeek.com/geeklist/258026/item/7127463#item7127463",
            "geeklist_host": "Venom Snake",
            "contributor": "Splatterthrash"
        },
        {
            "geeklist_id": "258026",
            "geeklist_item_id": "7132900",
            "year_month": "2019/08",
            "year": "2019",
            "month": "08",
            "geeklist_item_link": "https://boardgamegeek.com/geeklist/258026/item/7132900#item7132900",
            "geeklist_host": "Venom Snake",
            "contributor": "BunniCladwell"
        },
        {
            "geeklist_id": "260880",
            "geeklist_item_id": "7134685",
            "year_month": "2019/09",
            "year": "2019",
            "month": "09",
            "geeklist_item_link": "https://boardgamegeek.com/geeklist/260880/item/7134685#item7134685",
            "geeklist_host": "jgatkinsn",
            "contributor": "BunniCladwell"
        },
        {
            "geeklist_id": "260880",
            "geeklist_item_id": "7136645",
            "year_month": "2019/09",
            "year": "2019",
            "month": "09",
            "geeklist_item_link": "https://boardgamegeek.com/geeklist/260880/item/7136645#item7136645",
            "geeklist_host": "jgatkinsn",
            "contributor": "jeche"
        },
        {
            "geeklist_id": "260880",
            "geeklist_item_id": "7146687",
            "year_month": "2019/09",
            "year": "2019",
            "month": "09",
            "geeklist_item_link": "https://boardgamegeek.com/geeklist/260880/item/7146687#item7146687",
            "geeklist_host": "jgatkinsn",
            "contributor": "DocSavage2001"
        },
        {
            "geeklist_id": "260880",
            "geeklist_item_id": "7161579",
            "year_month": "2019/09",
            "year": "2019",
            "month": "09",
            "geeklist_item_link": "https://boardgamegeek.com/geeklist/260880/item/7161579#item7161579",
            "geeklist_host": "jgatkinsn",
            "contributor": "Poomba5150"
        },
        {
            "geeklist_id": "260880",
            "geeklist_item_id": "7161863",
            "year_month": "2019/09",
            "year": "2019",
            "month": "09",
            "geeklist_item_link": "https://boardgamegeek.com/geeklist/260880/item/7161863#item7161863",
            "geeklist_host": "jgatkinsn",
            "contributor": "Mishko"
        },
        {
            "geeklist_id": "260880",
            "geeklist_item_id": "7169683",
            "year_month": "2019/09",
            "year": "2019",
            "month": "09",
            "geeklist_item_link": "https://boardgamegeek.com/geeklist/260880/item/7169683#item7169683",
            "geeklist_host": "jgatkinsn",
            "contributor": "Annanicolesmith"
        },
        {
            "geeklist_id": "260880",
            "geeklist_item_id": "7176552",
            "year_month": "2019/09",
            "year": "2019",
            "month": "09",
            "geeklist_item_link": "https://boardgamegeek.com/geeklist/260880/item/7176552#item7176552",
            "geeklist_host": "jgatkinsn",
            "contributor": "Albia"
        },
        {
            "geeklist_id": "260880",
            "geeklist_item_id": "7177062",
            "year_month": "2019/09",
            "year": "2019",
            "month": "09",
            "geeklist_item_link": "https://boardgamegeek.com/geeklist/260880/item/7177062#item7177062",
            "geeklist_host": "jgatkinsn",
            "contributor": "Marctimmins89"
        },
        {
            "geeklist_id": "260880",
            "geeklist_item_id": "7185930",
            "year_month": "2019/09",
            "year": "2019",
            "month": "09",
            "geeklist_item_link": "https://boardgamegeek.com/geeklist/260880/item/7185930#item7185930",
            "geeklist_host": "jgatkinsn",
            "contributor": "repairmanjack"
        },
        {
            "geeklist_id": "260880",
            "geeklist_item_id": "7193156",
            "year_month": "2019/09",
            "year": "2019",
            "month": "09",
            "geeklist_item_link": "https://boardgamegeek.com/geeklist/260880/item/7193156#item7193156",
            "geeklist_host": "jgatkinsn",
            "contributor": "weyrbrat"
        },
        {
            "geeklist_id": "260880",
            "geeklist_item_id": "7202381",
            "year_month": "2019/09",
            "year": "2019",
            "month": "09",
            "geeklist_item_link": "https://boardgamegeek.com/geeklist/260880/item/7202381#item7202381",
            "geeklist_host": "jgatkinsn",
            "contributor": "crazybear"
        },
        {
            "geeklist_id": "260880",
            "geeklist_item_id": "7209216",
            "year_month": "2019/09",
            "year": "2019",
            "month": "09",
            "geeklist_item_link": "https://boardgamegeek.com/geeklist/260880/item/7209216#item7209216",
            "geeklist_host": "jgatkinsn",
            "contributor": "Annanicolesmith"
        },
        {
            "geeklist_id": "260880",
            "geeklist_item_id": "7214886",
            "year_month": "2019/09",
            "year": "2019",
            "month": "09",
            "geeklist_item_link": "https://boardgamegeek.com/geeklist/260880/item/7214886#item7214886",
            "geeklist_host": "jgatkinsn",
            "contributor": "Robble"
        },
        {
            "geeklist_id": "262008",
            "geeklist_item_id": "7365039",
            "year_month": "2019/12",
            "year": "2019",
            "month": "12",
            "geeklist_item_link": "https://boardgamegeek.com/geeklist/262008/item/7365039#item7365039",
            "geeklist_host": "jeffrhind",
            "contributor": "ojtBGG"
        },
        {
            "geeklist_id": "262008",
            "geeklist_item_id": "7380287",
            "year_month": "2019/12",
            "year": "2019",
            "month": "12",
            "geeklist_item_link": "https://boardgamegeek.com/geeklist/262008/item/7380287#item7380287",
            "geeklist_host": "jeffrhind",
            "contributor": "eastwoodk"
        },
        {
            "geeklist_id": "262008",
            "geeklist_item_id": "7380647",
            "year_month": "2019/12",
            "year": "2019",
            "month": "12",
            "geeklist_item_link": "https://boardgamegeek.com/geeklist/262008/item/7380647#item7380647",
            "geeklist_host": "jeffrhind",
            "contributor": "BunniCladwell"
        },
        {
            "geeklist_id": "262008",
            "geeklist_item_id": "7380955",
            "year_month": "2019/12",
            "year": "2019",
            "month": "12",
            "geeklist_item_link": "https://boardgamegeek.com/geeklist/262008/item/7380955#item7380955",
            "geeklist_host": "jeffrhind",
            "contributor": "ojtBGG"
        },
        {
            "geeklist_id": "262008",
            "geeklist_item_id": "7394226",
            "year_month": "2019/12",
            "year": "2019",
            "month": "12",
            "geeklist_item_link": "https://boardgamegeek.com/geeklist/262008/item/7394226#item7394226",
            "geeklist_host": "jeffrhind",
            "contributor": "weazom"
        },
        {
            "geeklist_id": "262008",
            "geeklist_item_id": "7410301",
            "year_month": "2019/12",
            "year": "2019",
            "month": "12",
            "geeklist_item_link": "https://boardgamegeek.com/geeklist/262008/item/7410301#item7410301",
            "geeklist_host": "jeffrhind",
            "contributor": "Arven"
        },
        {
            "geeklist_id": "262319",
            "geeklist_item_id": "7221445",
            "year_month": "2019/10",
            "year": "2019",
            "month": "10",
            "geeklist_item_link": "https://boardgamegeek.com/geeklist/262319/item/7221445#item7221445",
            "geeklist_host": "narcher007",
            "contributor": "DocSavage2001"
        },
        {
            "geeklist_id": "262319",
            "geeklist_item_id": "7226968",
            "year_month": "2019/10",
            "year": "2019",
            "month": "10",
            "geeklist_item_link": "https://boardgamegeek.com/geeklist/262319/item/7226968#item7226968",
            "geeklist_host": "narcher007",
            "contributor": "Haywood"
        },
        {
            "geeklist_id": "262319",
            "geeklist_item_id": "7233965",
            "year_month": "2019/10",
            "year": "2019",
            "month": "10",
            "geeklist_item_link": "https://boardgamegeek.com/geeklist/262319/item/7233965#item7233965",
            "geeklist_host": "narcher007",
            "contributor": "ojtBGG"
        },
        {
            "geeklist_id": "262319",
            "geeklist_item_id": "7235771",
            "year_month": "2019/10",
            "year": "2019",
            "month": "10",
            "geeklist_item_link": "https://boardgamegeek.com/geeklist/262319/item/7235771#item7235771",
            "geeklist_host": "narcher007",
            "contributor": "EmperorGestahl"
        },
        {
            "geeklist_id": "262319",
            "geeklist_item_id": "7238881",
            "year_month": "2019/10",
            "year": "2019",
            "month": "10",
            "geeklist_item_link": "https://boardgamegeek.com/geeklist/262319/item/7238881#item7238881",
            "geeklist_host": "narcher007",
            "contributor": "ParisPink"
        },
        {
            "geeklist_id": "262319",
            "geeklist_item_id": "7239680",
            "year_month": "2019/10",
            "year": "2019",
            "month": "10",
            "geeklist_item_link": "https://boardgamegeek.com/geeklist/262319/item/7239680#item7239680",
            "geeklist_host": "narcher007",
            "contributor": "Robble"
        },
        {
            "geeklist_id": "262319",
            "geeklist_item_id": "7243478",
            "year_month": "2019/10",
            "year": "2019",
            "month": "10",
            "geeklist_item_link": "https://boardgamegeek.com/geeklist/262319/item/7243478#item7243478",
            "geeklist_host": "narcher007",
            "contributor": "ParisPink"
        },
        {
            "geeklist_id": "262319",
            "geeklist_item_id": "7248266",
            "year_month": "2019/10",
            "year": "2019",
            "month": "10",
            "geeklist_item_link": "https://boardgamegeek.com/geeklist/262319/item/7248266#item7248266",
            "geeklist_host": "narcher007",
            "contributor": "Marctimmins89"
        },
        {
            "geeklist_id": "262319",
            "geeklist_item_id": "7250343",
            "year_month": "2019/10",
            "year": "2019",
            "month": "10",
            "geeklist_item_link": "https://boardgamegeek.com/geeklist/262319/item/7250343#item7250343",
            "geeklist_host": "narcher007",
            "contributor": "Windshield"
        },
        {
            "geeklist_id": "262319",
            "geeklist_item_id": "7255498",
            "year_month": "2019/10",
            "year": "2019",
            "month": "10",
            "geeklist_item_link": "https://boardgamegeek.com/geeklist/262319/item/7255498#item7255498",
            "geeklist_host": "narcher007",
            "contributor": "Albia"
        },
        {
            "geeklist_id": "262319",
            "geeklist_item_id": "7255967",
            "year_month": "2019/10",
            "year": "2019",
            "month": "10",
            "geeklist_item_link": "https://boardgamegeek.com/geeklist/262319/item/7255967#item7255967",
            "geeklist_host": "narcher007",
            "contributor": "desertrat2020"
        },
        {
            "geeklist_id": "262319",
            "geeklist_item_id": "7269842",
            "year_month": "2019/10",
            "year": "2019",
            "month": "10",
            "geeklist_item_link": "https://boardgamegeek.com/geeklist/262319/item/7269842#item7269842",
            "geeklist_host": "narcher007",
            "contributor": "EmperorGestahl"
        },
        {
            "geeklist_id": "262319",
            "geeklist_item_id": "7270197",
            "year_month": "2019/10",
            "year": "2019",
            "month": "10",
            "geeklist_item_link": "https://boardgamegeek.com/geeklist/262319/item/7270197#item7270197",
            "geeklist_host": "narcher007",
            "contributor": "vacuumdude"
        },
        {
            "geeklist_id": "262319",
            "geeklist_item_id": "7271508",
            "year_month": "2019/10",
            "year": "2019",
            "month": "10",
            "geeklist_item_link": "https://boardgamegeek.com/geeklist/262319/item/7271508#item7271508",
            "geeklist_host": "narcher007",
            "contributor": "Windshield"
        },
        {
            "geeklist_id": "262319",
            "geeklist_item_id": "7289345",
            "year_month": "2019/10",
            "year": "2019",
            "month": "10",
            "geeklist_item_link": "https://boardgamegeek.com/geeklist/262319/item/7289345#item7289345",
            "geeklist_host": "narcher007",
            "contributor": "dereklee9819"
        },
        {
            "geeklist_id": "262633",
            "geeklist_item_id": "7303330",
            "year_month": "2019/11",
            "year": "2019",
            "month": "11",
            "geeklist_item_link": "https://boardgamegeek.com/geeklist/262633/item/7303330#item7303330",
            "geeklist_host": "Albia",
            "contributor": "EmperorGestahl"
        },
        {
            "geeklist_id": "262633",
            "geeklist_item_id": "7332042",
            "year_month": "2019/11",
            "year": "2019",
            "month": "11",
            "geeklist_item_link": "https://boardgamegeek.com/geeklist/262633/item/7332042#item7332042",
            "geeklist_host": "Albia",
            "contributor": "Marctimmins89"
        },
        {
            "geeklist_id": "262633",
            "geeklist_item_id": "7337754",
            "year_month": "2019/11",
            "year": "2019",
            "month": "11",
            "geeklist_item_link": "https://boardgamegeek.com/geeklist/262633/item/7337754#item7337754",
            "geeklist_host": "Albia",
            "contributor": "reverendunclebastard"
        },
        {
            "geeklist_id": "262633",
            "geeklist_item_id": "7343889",
            "year_month": "2019/11",
            "year": "2019",
            "month": "11",
            "geeklist_item_link": "https://boardgamegeek.com/geeklist/262633/item/7343889#item7343889",
            "geeklist_host": "Albia",
            "contributor": "overhaul"
        },
        {
            "geeklist_id": "262633",
            "geeklist_item_id": "7352786",
            "year_month": "2019/11",
            "year": "2019",
            "month": "11",
            "geeklist_item_link": "https://boardgamegeek.com/geeklist/262633/item/7352786#item7352786",
            "geeklist_host": "Albia",
            "contributor": "overhaul"
        },
        {
            "geeklist_id": "262633",
            "geeklist_item_id": "7352932",
            "year_month": "2019/11",
            "year": "2019",
            "month": "11",
            "geeklist_item_link": "https://boardgamegeek.com/geeklist/262633/item/7352932#item7352932",
            "geeklist_host": "Albia",
            "contributor": "BunniCladwell"
        },
        {
            "geeklist_id": "262633",
            "geeklist_item_id": "7353679",
            "year_month": "2019/11",
            "year": "2019",
            "month": "11",
            "geeklist_item_link": "https://boardgamegeek.com/geeklist/262633/item/7353679#item7353679",
            "geeklist_host": "Albia",
            "contributor": "overhaul"
        },
        {
            "geeklist_id": "262633",
            "geeklist_item_id": "7354690",
            "year_month": "2019/11",
            "year": "2019",
            "month": "11",
            "geeklist_item_link": "https://boardgamegeek.com/geeklist/262633/item/7354690#item7354690",
            "geeklist_host": "Albia",
            "contributor": "permagoof"
        },
        {
            "geeklist_id": "262633",
            "geeklist_item_id": "7355728",
            "year_month": "2019/11",
            "year": "2019",
            "month": "11",
            "geeklist_item_link": "https://boardgamegeek.com/geeklist/262633/item/7355728#item7355728",
            "geeklist_host": "Albia",
            "contributor": "desertrat2020"
        },
        {
            "geeklist_id": "266487",
            "geeklist_item_id": "7430011",
            "year_month": "2020/01",
            "year": "2020",
            "month": "01",
            "geeklist_item_link": "https://boardgamegeek.com/geeklist/266487/item/7430011#item7430011",
            "geeklist_host": "jomurph86",
            "contributor": "ojtBGG"
        },
        {
            "geeklist_id": "266487",
            "geeklist_item_id": "7440603",
            "year_month": "2020/01",
            "year": "2020",
            "month": "01",
            "geeklist_item_link": "https://boardgamegeek.com/geeklist/266487/item/7440603#item7440603",
            "geeklist_host": "jomurph86",
            "contributor": "Registrau"
        },
        {
            "geeklist_id": "266487",
            "geeklist_item_id": "7440627",
            "year_month": "2020/01",
            "year": "2020",
            "month": "01",
            "geeklist_item_link": "https://boardgamegeek.com/geeklist/266487/item/7440627#item7440627",
            "geeklist_host": "jomurph86",
            "contributor": "Registrau"
        },
        {
            "geeklist_id": "266487",
            "geeklist_item_id": "7446119",
            "year_month": "2020/01",
            "year": "2020",
            "month": "01",
            "geeklist_item_link": "https://boardgamegeek.com/geeklist/266487/item/7446119#item7446119",
            "geeklist_host": "jomurph86",
            "contributor": "Registrau"
        },
        {
            "geeklist_id": "266487",
            "geeklist_item_id": "7447945",
            "year_month": "2020/01",
            "year": "2020",
            "month": "01",
            "geeklist_item_link": "https://boardgamegeek.com/geeklist/266487/item/7447945#item7447945",
            "geeklist_host": "jomurph86",
            "contributor": "Annanicolesmith"
        },
        {
            "geeklist_id": "266487",
            "geeklist_item_id": "7486973",
            "year_month": "2020/01",
            "year": "2020",
            "month": "01",
            "geeklist_item_link": "https://boardgamegeek.com/geeklist/266487/item/7486973#item7486973",
            "geeklist_host": "jomurph86",
            "contributor": "ojtBGG"
        },
        {
            "geeklist_id": "266487",
            "geeklist_item_id": "7494897",
            "year_month": "2020/01",
            "year": "2020",
            "month": "01",
            "geeklist_item_link": "https://boardgamegeek.com/geeklist/266487/item/7494897#item7494897",
            "geeklist_host": "jomurph86",
            "contributor": "BunniCladwell"
        },
        {
            "geeklist_id": "268583",
            "geeklist_item_id": "7501352",
            "year_month": "2020/02",
            "year": "2020",
            "month": "02",
            "geeklist_item_link": "https://boardgamegeek.com/geeklist/268583/item/7501352#item7501352",
            "geeklist_host": "Doc_H",
            "contributor": "raindrop77"
        },
        {
            "geeklist_id": "268583",
            "geeklist_item_id": "7507215",
            "year_month": "2020/02",
            "year": "2020",
            "month": "02",
            "geeklist_item_link": "https://boardgamegeek.com/geeklist/268583/item/7507215#item7507215",
            "geeklist_host": "Doc_H",
            "contributor": "ojtBGG"
        },
        {
            "geeklist_id": "268583",
            "geeklist_item_id": "7520209",
            "year_month": "2020/02",
            "year": "2020",
            "month": "02",
            "geeklist_item_link": "https://boardgamegeek.com/geeklist/268583/item/7520209#item7520209",
            "geeklist_host": "Doc_H",
            "contributor": "Zee5001"
        },
        {
            "geeklist_id": "268583",
            "geeklist_item_id": "7539489",
            "year_month": "2020/02",
            "year": "2020",
            "month": "02",
            "geeklist_item_link": "https://boardgamegeek.com/geeklist/268583/item/7539489#item7539489",
            "geeklist_host": "Doc_H",
            "contributor": "TheStoicEmperor"
        },
        {
            "geeklist_id": "268583",
            "geeklist_item_id": "7541173",
            "year_month": "2020/02",
            "year": "2020",
            "month": "02",
            "geeklist_item_link": "https://boardgamegeek.com/geeklist/268583/item/7541173#item7541173",
            "geeklist_host": "Doc_H",
            "contributor": "Windshield"
        },
        {
            "geeklist_id": "268583",
            "geeklist_item_id": "7541452",
            "year_month": "2020/02",
            "year": "2020",
            "month": "02",
            "geeklist_item_link": "https://boardgamegeek.com/geeklist/268583/item/7541452#item7541452",
            "geeklist_host": "Doc_H",
            "contributor": "Brenoit"
        },
        {
            "geeklist_id": "268583",
            "geeklist_item_id": "7554529",
            "year_month": "2020/02",
            "year": "2020",
            "month": "02",
            "geeklist_item_link": "https://boardgamegeek.com/geeklist/268583/item/7554529#item7554529",
            "geeklist_host": "Doc_H",
            "contributor": "HawkAnt"
        },
        {
            "geeklist_id": "268583",
            "geeklist_item_id": "7564918",
            "year_month": "2020/02",
            "year": "2020",
            "month": "02",
            "geeklist_item_link": "https://boardgamegeek.com/geeklist/268583/item/7564918#item7564918",
            "geeklist_host": "Doc_H",
            "contributor": "Octopusmountain"
        },
        {
            "geeklist_id": "269654",
            "geeklist_item_id": "7570835",
            "year_month": "2020/03",
            "year": "2020",
            "month": "03",
            "geeklist_item_link": "https://boardgamegeek.com/geeklist/269654/item/7570835#item7570835",
            "geeklist_host": "jwml",
            "contributor": "Jy0831"
        },
        {
            "geeklist_id": "269654",
            "geeklist_item_id": "7611528",
            "year_month": "2020/03",
            "year": "2020",
            "month": "03",
            "geeklist_item_link": "https://boardgamegeek.com/geeklist/269654/item/7611528#item7611528",
            "geeklist_host": "jwml",
            "contributor": "Eyefink"
        },
        {
            "geeklist_id": "269654",
            "geeklist_item_id": "7612209",
            "year_month": "2020/03",
            "year": "2020",
            "month": "03",
            "geeklist_item_link": "https://boardgamegeek.com/geeklist/269654/item/7612209#item7612209",
            "geeklist_host": "jwml",
            "contributor": "thredith"
        },
        {
            "geeklist_id": "269654",
            "geeklist_item_id": "7612641",
            "year_month": "2020/03",
            "year": "2020",
            "month": "03",
            "geeklist_item_link": "https://boardgamegeek.com/geeklist/269654/item/7612641#item7612641",
            "geeklist_host": "jwml",
            "contributor": "WingTale"
        },
        {
            "geeklist_id": "270349",
            "geeklist_item_id": "7625382",
            "year_month": "2020/04",
            "year": "2020",
            "month": "04",
            "geeklist_item_link": "https://boardgamegeek.com/geeklist/270349/item/7625382#item7625382",
            "geeklist_host": "threepointthed",
            "contributor": "Jy0831"
        },
        {
            "geeklist_id": "270349",
            "geeklist_item_id": "7632508",
            "year_month": "2020/04",
            "year": "2020",
            "month": "04",
            "geeklist_item_link": "https://boardgamegeek.com/geeklist/270349/item/7632508#item7632508",
            "geeklist_host": "threepointthed",
            "contributor": "Swizze"
        },
        {
            "geeklist_id": "270349",
            "geeklist_item_id": "7633859",
            "year_month": "2020/04",
            "year": "2020",
            "month": "04",
            "geeklist_item_link": "https://boardgamegeek.com/geeklist/270349/item/7633859#item7633859",
            "geeklist_host": "threepointthed",
            "contributor": "Swizze"
        },
        {
            "geeklist_id": "270349",
            "geeklist_item_id": "7642046",
            "year_month": "2020/04",
            "year": "2020",
            "month": "04",
            "geeklist_item_link": "https://boardgamegeek.com/geeklist/270349/item/7642046#item7642046",
            "geeklist_host": "threepointthed",
            "contributor": "Swizze"
        },
        {
            "geeklist_id": "270349",
            "geeklist_item_id": "7649889",
            "year_month": "2020/04",
            "year": "2020",
            "month": "04",
            "geeklist_item_link": "https://boardgamegeek.com/geeklist/270349/item/7649889#item7649889",
            "geeklist_host": "threepointthed",
            "contributor": "ojtBGG"
        },
        {
            "geeklist_id": "270349",
            "geeklist_item_id": "7652893",
            "year_month": "2020/04",
            "year": "2020",
            "month": "04",
            "geeklist_item_link": "https://boardgamegeek.com/geeklist/270349/item/7652893#item7652893",
            "geeklist_host": "threepointthed",
            "contributor": "SpaceAlien"
        },
        {
            "geeklist_id": "272126",
            "geeklist_item_id": "7663510",
            "year_month": "2020/05",
            "year": "2020",
            "month": "05",
            "geeklist_item_link": "https://boardgamegeek.com/geeklist/272126/item/7663510#item7663510",
            "geeklist_host": "gentle",
            "contributor": "SpaceAlien"
        },
        {
            "geeklist_id": "272126",
            "geeklist_item_id": "7672069",
            "year_month": "2020/05",
            "year": "2020",
            "month": "05",
            "geeklist_item_link": "https://boardgamegeek.com/geeklist/272126/item/7672069#item7672069",
            "geeklist_host": "gentle",
            "contributor": "Marctimmins89"
        },
        {
            "geeklist_id": "272126",
            "geeklist_item_id": "7678190",
            "year_month": "2020/05",
            "year": "2020",
            "month": "05",
            "geeklist_item_link": "https://boardgamegeek.com/geeklist/272126/item/7678190#item7678190",
            "geeklist_host": "gentle",
            "contributor": "Jy0831"
        },
        {
            "geeklist_id": "272126",
            "geeklist_item_id": "7680275",
            "year_month": "2020/05",
            "year": "2020",
            "month": "05",
            "geeklist_item_link": "https://boardgamegeek.com/geeklist/272126/item/7680275#item7680275",
            "geeklist_host": "gentle",
            "contributor": "jgatkinsn"
        },
        {
            "geeklist_id": "272126",
            "geeklist_item_id": "7682241",
            "year_month": "2020/05",
            "year": "2020",
            "month": "05",
            "geeklist_item_link": "https://boardgamegeek.com/geeklist/272126/item/7682241#item7682241",
            "geeklist_host": "gentle",
            "contributor": "Annanicolesmith"
        },
        {
            "geeklist_id": "272126",
            "geeklist_item_id": "7683542",
            "year_month": "2020/05",
            "year": "2020",
            "month": "05",
            "geeklist_item_link": "https://boardgamegeek.com/geeklist/272126/item/7683542#item7683542",
            "geeklist_host": "gentle",
            "contributor": "custom golf clubs"
        },
        {
            "geeklist_id": "272126",
            "geeklist_item_id": "7684661",
            "year_month": "2020/05",
            "year": "2020",
            "month": "05",
            "geeklist_item_link": "https://boardgamegeek.com/geeklist/272126/item/7684661#item7684661",
            "geeklist_host": "gentle",
            "contributor": "MeepleRiot"
        },
        {
            "geeklist_id": "272126",
            "geeklist_item_id": "7684946",
            "year_month": "2020/05",
            "year": "2020",
            "month": "05",
            "geeklist_item_link": "https://boardgamegeek.com/geeklist/272126/item/7684946#item7684946",
            "geeklist_host": "gentle",
            "contributor": "jgatkinsn"
        },
        {
            "geeklist_id": "272126",
            "geeklist_item_id": "7691021",
            "year_month": "2020/05",
            "year": "2020",
            "month": "05",
            "geeklist_item_link": "https://boardgamegeek.com/geeklist/272126/item/7691021#item7691021",
            "geeklist_host": "gentle",
            "contributor": "raindrop77"
        },
        {
            "geeklist_id": "273040",
            "geeklist_item_id": "7712808",
            "year_month": "2020/06",
            "year": "2020",
            "month": "06",
            "geeklist_item_link": "https://boardgamegeek.com/geeklist/273040/item/7712808#item7712808",
            "geeklist_host": "Elida",
            "contributor": "Swizze"
        },
        {
            "geeklist_id": "273040",
            "geeklist_item_id": "7715538",
            "year_month": "2020/06",
            "year": "2020",
            "month": "06",
            "geeklist_item_link": "https://boardgamegeek.com/geeklist/273040/item/7715538#item7715538",
            "geeklist_host": "Elida",
            "contributor": "Jy0831"
        },
        {
            "geeklist_id": "273040",
            "geeklist_item_id": "7719328",
            "year_month": "2020/06",
            "year": "2020",
            "month": "06",
            "geeklist_item_link": "https://boardgamegeek.com/geeklist/273040/item/7719328#item7719328",
            "geeklist_host": "Elida",
            "contributor": "jeffrhind"
        },
        {
            "geeklist_id": "273040",
            "geeklist_item_id": "7728309",
            "year_month": "2020/06",
            "year": "2020",
            "month": "06",
            "geeklist_item_link": "https://boardgamegeek.com/geeklist/273040/item/7728309#item7728309",
            "geeklist_host": "Elida",
            "contributor": "MeepleRiot"
        },
        {
            "geeklist_id": "273040",
            "geeklist_item_id": "7733575",
            "year_month": "2020/06",
            "year": "2020",
            "month": "06",
            "geeklist_item_link": "https://boardgamegeek.com/geeklist/273040/item/7733575#item7733575",
            "geeklist_host": "Elida",
            "contributor": "ojtBGG"
        },
        {
            "geeklist_id": "273040",
            "geeklist_item_id": "7736178",
            "year_month": "2020/06",
            "year": "2020",
            "month": "06",
            "geeklist_item_link": "https://boardgamegeek.com/geeklist/273040/item/7736178#item7736178",
            "geeklist_host": "Elida",
            "contributor": "jgatkinsn"
        },
        {
            "geeklist_id": "273040",
            "geeklist_item_id": "7738421",
            "year_month": "2020/06",
            "year": "2020",
            "month": "06",
            "geeklist_item_link": "https://boardgamegeek.com/geeklist/273040/item/7738421#item7738421",
            "geeklist_host": "Elida",
            "contributor": "Annanicolesmith"
        },
        {
            "geeklist_id": "273040",
            "geeklist_item_id": "7743892",
            "year_month": "2020/06",
            "year": "2020",
            "month": "06",
            "geeklist_item_link": "https://boardgamegeek.com/geeklist/273040/item/7743892#item7743892",
            "geeklist_host": "Elida",
            "contributor": "MeepleRiot"
        },
        {
            "geeklist_id": "274323",
            "geeklist_item_id": "7745285",
            "year_month": "2020/07",
            "year": "2020",
            "month": "07",
            "geeklist_item_link": "https://boardgamegeek.com/geeklist/274323/item/7745285#item7745285",
            "geeklist_host": "repairmanjack",
            "contributor": "Jy0831"
        },
        {
            "geeklist_id": "274323",
            "geeklist_item_id": "7746924",
            "year_month": "2020/07",
            "year": "2020",
            "month": "07",
            "geeklist_item_link": "https://boardgamegeek.com/geeklist/274323/item/7746924#item7746924",
            "geeklist_host": "repairmanjack",
            "contributor": "Annanicolesmith"
        },
        {
            "geeklist_id": "274323",
            "geeklist_item_id": "7752089",
            "year_month": "2020/07",
            "year": "2020",
            "month": "07",
            "geeklist_item_link": "https://boardgamegeek.com/geeklist/274323/item/7752089#item7752089",
            "geeklist_host": "repairmanjack",
            "contributor": "Marctimmins89"
        },
        {
            "geeklist_id": "274323",
            "geeklist_item_id": "7760024",
            "year_month": "2020/07",
            "year": "2020",
            "month": "07",
            "geeklist_item_link": "https://boardgamegeek.com/geeklist/274323/item/7760024#item7760024",
            "geeklist_host": "repairmanjack",
            "contributor": "MeepleRiot"
        },
        {
            "geeklist_id": "274323",
            "geeklist_item_id": "7762208",
            "year_month": "2020/07",
            "year": "2020",
            "month": "07",
            "geeklist_item_link": "https://boardgamegeek.com/geeklist/274323/item/7762208#item7762208",
            "geeklist_host": "repairmanjack",
            "contributor": "gobo1572"
        },
        {
            "geeklist_id": "274323",
            "geeklist_item_id": "7779847",
            "year_month": "2020/07",
            "year": "2020",
            "month": "07",
            "geeklist_item_link": "https://boardgamegeek.com/geeklist/274323/item/7779847#item7779847",
            "geeklist_host": "repairmanjack",
            "contributor": "Marctimmins89"
        },
        {
            "geeklist_id": "274323",
            "geeklist_item_id": "7781004",
            "year_month": "2020/07",
            "year": "2020",
            "month": "07",
            "geeklist_item_link": "https://boardgamegeek.com/geeklist/274323/item/7781004#item7781004",
            "geeklist_host": "repairmanjack",
            "contributor": "DoxaLogos"
        },
        {
            "geeklist_id": "274323",
            "geeklist_item_id": "7787102",
            "year_month": "2020/07",
            "year": "2020",
            "month": "07",
            "geeklist_item_link": "https://boardgamegeek.com/geeklist/274323/item/7787102#item7787102",
            "geeklist_host": "repairmanjack",
            "contributor": "Swizze"
        },
        {
            "geeklist_id": "275246",
            "geeklist_item_id": "7797092",
            "year_month": "2020/08",
            "year": "2020",
            "month": "08",
            "geeklist_item_link": "https://boardgamegeek.com/geeklist/275246/item/7797092#item7797092",
            "geeklist_host": "mithoron",
            "contributor": "Jy0831"
        },
        {
            "geeklist_id": "275246",
            "geeklist_item_id": "7798180",
            "year_month": "2020/08",
            "year": "2020",
            "month": "08",
            "geeklist_item_link": "https://boardgamegeek.com/geeklist/275246/item/7798180#item7798180",
            "geeklist_host": "mithoron",
            "contributor": "patton55"
        },
        {
            "geeklist_id": "275246",
            "geeklist_item_id": "7800177",
            "year_month": "2020/08",
            "year": "2020",
            "month": "08",
            "geeklist_item_link": "https://boardgamegeek.com/geeklist/275246/item/7800177#item7800177",
            "geeklist_host": "mithoron",
            "contributor": "Annanicolesmith"
        },
        {
            "geeklist_id": "275246",
            "geeklist_item_id": "7807172",
            "year_month": "2020/08",
            "year": "2020",
            "month": "08",
            "geeklist_item_link": "https://boardgamegeek.com/geeklist/275246/item/7807172#item7807172",
            "geeklist_host": "mithoron",
            "contributor": "ojtBGG"
        },
        {
            "geeklist_id": "276177",
            "geeklist_item_id": "7847094",
            "year_month": "2020/09",
            "year": "2020",
            "month": "09",
            "geeklist_item_link": "https://boardgamegeek.com/geeklist/276177/item/7847094#item7847094",
            "geeklist_host": "DoxaLogos",
            "contributor": "Doc_H"
        },
        {
            "geeklist_id": "276177",
            "geeklist_item_id": "7852362",
            "year_month": "2020/09",
            "year": "2020",
            "month": "09",
            "geeklist_item_link": "https://boardgamegeek.com/geeklist/276177/item/7852362#item7852362",
            "geeklist_host": "DoxaLogos",
            "contributor": "Jy0831"
        },
        {
            "geeklist_id": "276177",
            "geeklist_item_id": "7859413",
            "year_month": "2020/09",
            "year": "2020",
            "month": "09",
            "geeklist_item_link": "https://boardgamegeek.com/geeklist/276177/item/7859413#item7859413",
            "geeklist_host": "DoxaLogos",
            "contributor": "Marctimmins89"
        },
        {
            "geeklist_id": "276177",
            "geeklist_item_id": "7864667",
            "year_month": "2020/09",
            "year": "2020",
            "month": "09",
            "geeklist_item_link": "https://boardgamegeek.com/geeklist/276177/item/7864667#item7864667",
            "geeklist_host": "DoxaLogos",
            "contributor": "Kryne7"
        },
        {
            "geeklist_id": "277289",
            "geeklist_item_id": "7921214",
            "year_month": "2020/10",
            "year": "2020",
            "month": "10",
            "geeklist_item_link": "https://boardgamegeek.com/geeklist/277289/item/7921214#item7921214",
            "geeklist_host": "Elida",
            "contributor": "ankno"
        },
        {
            "geeklist_id": "277289",
            "geeklist_item_id": "7939888",
            "year_month": "2020/10",
            "year": "2020",
            "month": "10",
            "geeklist_item_link": "https://boardgamegeek.com/geeklist/277289/item/7939888#item7939888",
            "geeklist_host": "Elida",
            "contributor": "game green"
        },
        {
            "geeklist_id": "278237",
            "geeklist_item_id": "7976347",
            "year_month": "2020/11",
            "year": "2020",
            "month": "11",
            "geeklist_item_link": "https://boardgamegeek.com/geeklist/278237/item/7976347#item7976347",
            "geeklist_host": "Albia",
            "contributor": "Brenoit"
        },
        {
            "geeklist_id": "278237",
            "geeklist_item_id": "7976856",
            "year_month": "2020/11",
            "year": "2020",
            "month": "11",
            "geeklist_item_link": "https://boardgamegeek.com/geeklist/278237/item/7976856#item7976856",
            "geeklist_host": "Albia",
            "contributor": "overhaul"
        },
        {
            "geeklist_id": "278237",
            "geeklist_item_id": "7979319",
            "year_month": "2020/11",
            "year": "2020",
            "month": "11",
            "geeklist_item_link": "https://boardgamegeek.com/geeklist/278237/item/7979319#item7979319",
            "geeklist_host": "Albia",
            "contributor": "Thripster"
        },
        {
            "geeklist_id": "279491",
            "geeklist_item_id": "8038412",
            "year_month": "2020/12",
            "year": "2020",
            "month": "12",
            "geeklist_item_link": "https://boardgamegeek.com/geeklist/279491/item/8038412#item8038412",
            "geeklist_host": "airzonk1",
            "contributor": "djott70"
        },
        {
            "geeklist_id": "279491",
            "geeklist_item_id": "8042964",
            "year_month": "2020/12",
            "year": "2020",
            "month": "12",
            "geeklist_item_link": "https://boardgamegeek.com/geeklist/279491/item/8042964#item8042964",
            "geeklist_host": "airzonk1",
            "contributor": "djott70"
        },
        {
            "geeklist_id": "279491",
            "geeklist_item_id": "8046281",
            "year_month": "2020/12",
            "year": "2020",
            "month": "12",
            "geeklist_item_link": "https://boardgamegeek.com/geeklist/279491/item/8046281#item8046281",
            "geeklist_host": "airzonk1",
            "contributor": "djott70"
        },
        {
            "geeklist_id": "279491",
            "geeklist_item_id": "8077589",
            "year_month": "2020/12",
            "year": "2020",
            "month": "12",
            "geeklist_item_link": "https://boardgamegeek.com/geeklist/279491/item/8077589#item8077589",
            "geeklist_host": "airzonk1",
            "contributor": "rainbowrose"
        },
        {
            "geeklist_id": "280864",
            "geeklist_item_id": "8050396",
            "year_month": "2021/01",
            "year": "2021",
            "month": "01",
            "geeklist_item_link": "https://boardgamegeek.com/geeklist/280864/item/8050396#item8050396",
            "geeklist_host": "Swizze",
            "contributor": "Swizze"
        },
        {
            "geeklist_id": "280864",
            "geeklist_item_id": "8055751",
            "year_month": "2021/01",
            "year": "2021",
            "month": "01",
            "geeklist_item_link": "https://boardgamegeek.com/geeklist/280864/item/8055751#item8055751",
            "geeklist_host": "Swizze",
            "contributor": "djott70"
        },
        {
            "geeklist_id": "280864",
            "geeklist_item_id": "8059579",
            "year_month": "2021/01",
            "year": "2021",
            "month": "01",
            "geeklist_item_link": "https://boardgamegeek.com/geeklist/280864/item/8059579#item8059579",
            "geeklist_host": "Swizze",
            "contributor": "djott70"
        },
        {
            "geeklist_id": "280864",
            "geeklist_item_id": "8077692",
            "year_month": "2021/01",
            "year": "2021",
            "month": "01",
            "geeklist_item_link": "https://boardgamegeek.com/geeklist/280864/item/8077692#item8077692",
            "geeklist_host": "Swizze",
            "contributor": "Haywood"
        },
        {
            "geeklist_id": "280864",
            "geeklist_item_id": "8078933",
            "year_month": "2021/01",
            "year": "2021",
            "month": "01",
            "geeklist_item_link": "https://boardgamegeek.com/geeklist/280864/item/8078933#item8078933",
            "geeklist_host": "Swizze",
            "contributor": "rainbowrose"
        },
        {
            "geeklist_id": "280864",
            "geeklist_item_id": "8087097",
            "year_month": "2021/01",
            "year": "2021",
            "month": "01",
            "geeklist_item_link": "https://boardgamegeek.com/geeklist/280864/item/8087097#item8087097",
            "geeklist_host": "Swizze",
            "contributor": "Swizze"
        },
        {
            "geeklist_id": "280864",
            "geeklist_item_id": "8101173",
            "year_month": "2021/01",
            "year": "2021",
            "month": "01",
            "geeklist_item_link": "https://boardgamegeek.com/geeklist/280864/item/8101173#item8101173",
            "geeklist_host": "Swizze",
            "contributor": "Nickxvan1"
        },
        {
            "geeklist_id": "280864",
            "geeklist_item_id": "8110333",
            "year_month": "2021/01",
            "year": "2021",
            "month": "01",
            "geeklist_item_link": "https://boardgamegeek.com/geeklist/280864/item/8110333#item8110333",
            "geeklist_host": "Swizze",
            "contributor": "djott70"
        },
        {
            "geeklist_id": "280864",
            "geeklist_item_id": "8112445",
            "year_month": "2021/01",
            "year": "2021",
            "month": "01",
            "geeklist_item_link": "https://boardgamegeek.com/geeklist/280864/item/8112445#item8112445",
            "geeklist_host": "Swizze",
            "contributor": "djott70"
        },
        {
            "geeklist_id": "282453",
            "geeklist_item_id": "8128154",
            "year_month": "2021/02",
            "year": "2021",
            "month": "02",
            "geeklist_item_link": "https://boardgamegeek.com/geeklist/282453/item/8128154#item8128154",
            "geeklist_host": "ArianneH",
            "contributor": "abendoso"
        },
        {
            "geeklist_id": "282453",
            "geeklist_item_id": "8146054",
            "year_month": "2021/02",
            "year": "2021",
            "month": "02",
            "geeklist_item_link": "https://boardgamegeek.com/geeklist/282453/item/8146054#item8146054",
            "geeklist_host": "ArianneH",
            "contributor": "djott70"
        },
        {
            "geeklist_id": "282453",
            "geeklist_item_id": "8147372",
            "year_month": "2021/02",
            "year": "2021",
            "month": "02",
            "geeklist_item_link": "https://boardgamegeek.com/geeklist/282453/item/8147372#item8147372",
            "geeklist_host": "ArianneH",
            "contributor": "djott70"
        },
        {
            "geeklist_id": "282453",
            "geeklist_item_id": "8160549",
            "year_month": "2021/02",
            "year": "2021",
            "month": "02",
            "geeklist_item_link": "https://boardgamegeek.com/geeklist/282453/item/8160549#item8160549",
            "geeklist_host": "ArianneH",
            "contributor": "patton55"
        }
    ],
    "sgoyt_count_249922": 22,
    "sgoyt_count_251846": 14,
    "sgoyt_count_251880": 19,
    "sgoyt_count_252324": 9,
    "sgoyt_count_253515": 12,
    "sgoyt_count_255931": 10,
    "sgoyt_count_256394": 16,
    "sgoyt_count_258026": 11,
    "sgoyt_count_260880": 13,
    "sgoyt_count_262008": 6,
    "sgoyt_count_262319": 15,
    "sgoyt_count_262633": 9,
    "sgoyt_count_266487": 7,
    "sgoyt_count_268583": 8,
    "sgoyt_count_269654": 4,
    "sgoyt_count_270349": 6,
    "sgoyt_count_272126": 9,
    "sgoyt_count_273040": 8,
    "sgoyt_count_274323": 8,
    "sgoyt_count_275246": 4,
    "sgoyt_count_276177": 4,
    "sgoyt_count_277289": 2,
    "sgoyt_count_278237": 3,
    "sgoyt_count_279491": 4,
    "sgoyt_count_280864": 9,
    "sgoyt_count_282453": 4,
    "sgoyt_count_156765": 0,
    "sgoyt_count_157888": 0,
    "sgoyt_count_158763": 0,
    "sgoyt_count_160445": 0,
    "sgoyt_count_161764": 0,
    "sgoyt_count_163198": 0,
    "sgoyt_count_164593": 0,
    "sgoyt_count_166060": 0,
    "sgoyt_count_169311": 0,
    "sgoyt_count_170533": 0,
    "sgoyt_count_171598": 0,
    "sgoyt_count_172996": 0,
    "sgoyt_count_174241": 0,
    "sgoyt_count_175551": 0,
    "sgoyt_count_176697": 0,
    "sgoyt_count_178257": 0,
    "sgoyt_count_178963": 0,
    "sgoyt_count_179645": 0,
    "sgoyt_count_182515": 0,
    "sgoyt_count_182573": 0,
    "sgoyt_count_183994": 0,
    "sgoyt_count_186058": 0,
    "sgoyt_count_186592": 0,
    "sgoyt_count_190679": 0,
    "sgoyt_count_191963": 0,
    "sgoyt_count_193005": 0,
    "sgoyt_count_194479": 0,
    "sgoyt_count_194940": 0,
    "sgoyt_count_197513": 0,
    "sgoyt_count_198923": 0,
    "sgoyt_count_200203": 0,
    "sgoyt_count_202271": 0,
    "sgoyt_count_204546": 0,
    "sgoyt_count_205877": 0,
    "sgoyt_count_206595": 0,
    "sgoyt_count_208306": 0,
    "sgoyt_count_209493": 0,
    "sgoyt_count_210694": 0,
    "sgoyt_count_211592": 0,
    "sgoyt_count_213557": 0,
    "sgoyt_count_214406": 0,
    "sgoyt_count_215297": 0,
    "sgoyt_count_217780": 0,
    "sgoyt_count_219163": 0,
    "sgoyt_count_221242": 0,
    "sgoyt_count_222478": 0,
    "sgoyt_count_223793": 0,
    "sgoyt_count_223927": 0,
    "sgoyt_count_225998": 0,
    "sgoyt_count_227011": 0,
    "sgoyt_count_228234": 0,
    "sgoyt_count_229124": 0,
    "sgoyt_count_229952": 0,
    "sgoyt_count_231127": 0,
    "sgoyt_count_233358": 0,
    "sgoyt_count_235012": 0,
    "sgoyt_count_237172": 0,
    "sgoyt_count_238328": 0,
    "sgoyt_count_238369": 0,
    "sgoyt_count_240624": 0,
    "sgoyt_count_241528": 0,
    "sgoyt_count_241745": 0,
    "sgoyt_count_242306": 0,
    "sgoyt_count_244471": 0,
    "sgoyt_count_245355": 0,
    "sgoyt_count_246401": 0,
    "sgoyt_count_247302": 0,
    "sgoyt_count_281198": 0,
    "sgoyt_count": 236,
    "thumbnail": "https://cf.geekdo-images.com/yLZJCVLlIx4c7eJEWUNJ7w__thumb/img/VNToqgS2-pOGU6MuvIkMPKn_y-s=/fit-in/200x150/filters:strip_icc()/pic4458123.jpg",
    "year_published": "2019",
    "designers": [
        "Elizabeth Hargrave"
    ],
    "weight": 2.42,
    "rating": 8.11,
    "play_time": "40 - 70",
    "best": "63",
    "recommended": "371",
    "not_recommended": "132",
    "categories": [
        "Animals",
        "Card Game",
        "Educational"
    ],
    "mechanics": [
        "Card Drafting",
        "Dice Rolling",
        "Drafting",
        "End Game Bonuses",
        "Hand Management",
        "Set Collection",
        "Solo / Solitaire Game"
    ],
    "expansions": [
        {
            "expansion_id": "290448",
            "expansion_name": "Wingspan: European Expansion",
            "expansion_bgg_link": "https://boardgamegeek.com/boardgame/290448"
        },
        {
            "expansion_id": "300580",
            "expansion_name": "Wingspan: Oceania Expansion",
            "expansion_bgg_link": "https://boardgamegeek.com/boardgame/300580"
        },
        {
            "expansion_id": "290837",
            "expansion_name": "Wingspan: Swift-Start Promo Pack",
            "expansion_bgg_link": "https://boardgamegeek.com/boardgame/290837"
        }
    ],
    "expansion_for": [],
    "designers_string": "Elizabeth Hargrave",
    "categories_string": "Animals; Card Game; Educational",
    "mechanics_string": "Card Drafting; Dice Rolling; Drafting; End Game Bonuses; Hand Management; Set Collection; Solo / Solitaire Game",
    "expansions_string": "{'expansion_id': '290448', 'expansion_name': 'Wingspan: European Expansion', 'expansion_bgg_link': 'https://boardgamegeek.com/boardgame/290448'}; {'expansion_id': '300580', 'expansion_name': 'Wingspan: Oceania Expansion', 'expansion_bgg_link': 'https://boardgamegeek.com/boardgame/300580'}; {'expansion_id': '290837', 'expansion_name': 'Wingspan: Swift-Start Promo Pack', 'expansion_bgg_link': 'https://boardgamegeek.com/boardgame/290837'}",
    "expansions_for_string": ""
}